Workbook

Sheet 最新价格
A1: 抓取时间 | B1: 游戏名 | C1: 版本 | D1: 商品标题 | E1: 价格 | F1: 卖家 | G1: 地区 | H1: 商品链接 | I1: 宣传图路径 | J1: 卡带信息图路径 | K1: 商品描述 | L1: 成色
A2: 2026-07-06 21:01:36 | B2: 塞尔达传说：王国之泪 | C2: 卡带 | D2: 出闲置 Switch《塞尔达传说：王国之泪》中文卡带，几乎全 新，带原装盒，插卡即玩，正版实体卡，非偏远地区包邮，不议价，砍价不回，喜欢直接拍，细节私聊。 | E2: 230 | F2: 去码头卖点咸鱼 | G2: 上海 | H2: https://www.goofish.com/item/1065525172471
A3: 2026-07-06 21:01:36 | B3: 塞尔达传说：王国之泪 | C3: 卡带 | D3: 几乎全新Switch《塞尔达传说：王国之泪》港版中文卡带，带 原装盒子，卡带盘面干净，金手指亮，插卡即玩，支持所有Switch主机，国行也能用，中文界面，支持amiibo，联机没问题，动作冒险类，6岁以上都能玩，内容齐全，无划痕，无异常，读卡没问题，功能正常，插上就能玩，补坑收藏都合适。 同城可自提，价格好说，喜欢直接拍，细节图私聊发～ | E3: 225 | F3: 郑习惯的电玩小店 | G3: 广东 | H3: https://www.goofish.com/item/1063556538180
A4: 2026-07-06 21:01:36 | B4: 塞尔达传说：王国之泪 | C4: 卡带 | D4: 【现货直发】 塞尔达传说王国之泪典藏版含卡带港版中文 实体卡 带 | E4: 480 | F4: 高品质正品百货店 | G4: 广东 | H4: https://www.goofish.com/item/1053308770307
A5: 2026-07-06 21:01:36 | B5: 塞尔达传说：王国之泪 | C5: 卡带 | D5: Nintendo Switch 塞尔达传说：王国之泪 美版卡 带，带原包装盒，正版实体卡，插卡即玩，支持所有Switch主机（国行/港版/日版/欧美版都能用），动作冒险类，玩法自由，探索创造，amiibo兼容，聚会、朋友、家庭都适合，塞尔达系列粉丝必入～ 卡带和盒子保存很好，轻微划痕磨损，读卡正常，到手即玩！ 包邮，可自提，喜欢直接拍或私聊细节图～ 分类：Switch游戏卡带 成色：轻微划痕 | E5: 245 | F5: 新手铲屎官 | G5: 北京 | H5: https://www.goofish.com/item/1065444324578
A6: 2026-07-06 21:01:36 | B6: 塞尔达传说：王国之泪 | C6: 卡带 | D6: Switch 塞尔达传说 王国之泪 港版中文卡带 几乎全新 带原装盒 卡带读取正常 包邮非偏远 喜欢直接拍 | E6: 239 | F6: 啦啦lllllll6 | G6: 北京 | H6: https://www.goofish.com/item/1034339190197
A7: 2026-07-06 21:01:36 | B7: 塞尔达传说：王国之泪 | C7: 卡带 | D7: 【包邮】Switch 塞尔达传说 王国之泪 中文卡带 几乎全新，带原装盒，正版实体卡带，插卡即玩，支持所有Switch主机，中文界面，动作冒险经典，玩法丰富，适合喜欢塞尔达系列和冒险游戏的朋友！ 【一】24小时内发货，包邮，新疆西藏补运费 【二】游戏有中文，支持所有Switch主机 【三】带原装盒，外观保存很好 【四】放心购买，不读卡不能玩包退，来回运费我承担 【五】不玩了包回收，走闲鱼，回收有 | E7: 238 | F7: 奥尔良电玩家 | G7: 天津 | H7: https://www.goofish.com/item/1057461010835
A8: 2026-07-06 21:01:36 | B8: 塞尔达传说：王国之泪 | C8: 卡带 | D8: 几乎全新Switch《塞尔达传说：王国之泪》港版中文卡带，带 原装盒子，保存很不错，卡带盘面干净，金手指无划痕，插卡即玩，支持所有Switch主机，国行也能用，中文界面，支持amiibo，联机没问题，动作冒险经典神作，画面超美，玩法丰富，6岁以上都能玩，盒子和卡带都在，内容齐全，读卡正常，功能无异常，放心入。 同城可自提，价格好说，喜欢直接拍，细节图私聊发～ | E8: 210 | F8: 郑习惯的电玩小店 | G8: 广东 | H8: https://www.goofish.com/item/1062746051297
A9: 2026-07-06 21:01:36 | B9: 塞尔达传说：王国之泪 | C9: 卡带 | D9: Switch 塞尔达传说 王国之泪 中文卡带，插卡即玩，支持 中文，画面精美，玩法丰富，动作冒险经典，喜欢塞尔达的朋友别错过。卡带保存很好，功能正常，成色实图所拍，看准再下单，售出不退不换。非偏远地区包邮，偏远地区补差5元，售后需要提供完整开箱视频 | E9: 222 | F9: 欧洲贴地爬行的雷电水母 | G9: 广东 | H9: https://www.goofish.com/item/1065071636384
A10: 2026-07-06 21:01:36 | B10: 塞尔达传说：王国之泪 | C10: 卡带 | D10: switch 塞尔达传说 王国之泪 港版 中文卡带 几乎全新，已通关，带原装盒和卡带 支持中文，支持amiibo，所有Switch主机通用 包邮，不退不换 需要直接拍，有问题私聊 | E10: 240 | F10: 办公室骑摩托的蓝带鱼 | G10: 北京 | H10: https://www.goofish.com/item/1044177782357
A11: 2026-07-06 21:01:36 | B11: 塞尔达传说：王国之泪 | C11: 卡带 | D11: 塞尔达王国之泪 港版中文卡带，带原装盒，成色几乎全新，插卡即 玩，支持所有Switch主机，简体中文，动作冒险经典，剧情画面都很棒，适合自用或收藏，包邮 杭州临平附近可自提，喜欢直接拍，细节私聊 | E11: 240 | F11: 臭垃圾佬 | G11: 浙江 | H11: https://www.goofish.com/item/1064962448011
A12: 2026-07-06 21:01:36 | B12: 塞尔达传说：王国之泪 | C12: 卡带 | D12: switch塞尔达传说 王国之泪 中文卡带，插卡即玩，支持所 有Switch主机，日版也能用。卡带保存很好，盒子完整，功能正常，成色实图所拍，适合喜欢塞尔达系列和动作冒险游戏的朋友收藏或自用。二手卡带，功能正常，成色实图所拍，看准再下单，售出不退不换。非偏远地区包邮，偏远地区补差5元，售后需要提供完整开箱视频 | E12: 222 | F12: 欧洲贴地爬行的雷电水母 | G12: 广东 | H12: https://www.goofish.com/item/1063118754379
A13: 2026-07-06 21:01:36 | B13: 塞尔达传说：王国之泪 | C13: 卡带 | D13: 塞尔达传说王国之泪 switch实体游戏卡带 二手带盒 二手外版带盒无损，版本随机，读卡正常 已清洁消毒。 包邮非偏远地区 不管在哪买的，玩腻或者通关都支持回收 | E13: 224.8 | F13: 桃源电玩 | G13: 广东 | H13: https://www.goofish.com/item/1045929876220
... A61: 2026-07-06 21:01:36 | B61: 塞尔达传说：王国之泪 | C61: 卡带 | D61: 几乎全新Switch《塞尔达传说：王国之泪》港版中文卡带，带 原装盒，插卡即玩，支持所有Switch主机，国行/港版/日版都能用，中文界面，动作冒险神作，适合6岁以上玩家！ 卡带外观很新，盒子包装都在，盘面干净没划痕，保存得很不错，正版保证，收藏自用都合适～ 包邮！支持自提，价格可聊，喜欢直接拍，细节图私聊发～ | E61: 225 | F61: flora666h | G61: 浙江 | H61: https://www.goofish.com/item/1060500643487
A62: 2026-07-06 21:01:36 | B62: 塞尔达传说：王国之泪 | C62: 卡带 | D62: 塞尔达传说王国之泪Switch卡带任天堂Switch游戏《塞 尔达传说：王国之泪》实体卡带，支持中文，兼容所有Switch主机。卡带外观整洁，金手指无氧化，插拔顺畅，功能正常，带盒。 | E62: 230 | G62: 河南 | H62: https://www.goofish.com/item/1065168564507
A63: 2026-07-06 21:01:36 | B63: 塞尔达传说：王国之泪 | C63: 卡带 | D63: 塞尔达传说王国之泪实体卡 接近全新 中文版 可以直接拍 图为购买记录 | E63: 230 | F63: 游塵 | G63: 北京 | H63: https://www.goofish.com/item/1055647935424
A64: 2026-07-06 21:01:36 | B64: 塞尔达传说：王国之泪 | C64: 卡带 | D64: Switch《塞尔达传说 王国之泪》港版中文，仅插拔2次，几 乎全新，带原包装盒，正版实体卡带，内容完整，插卡即玩，支持所有Switch主机，动作冒险经典，可直拍 | E64: 235 | F64: 叶芽Leafbud | G64: 河北 | H64: https://www.goofish.com/item/1057493056166
A65: 2026-07-06 21:01:36 | B65: 塞尔达传说：王国之泪 | C65: 卡带 | D65: 几乎全新Switch《塞尔达传说：王国之泪》日版卡带，带原装 盒子，盘面干净，保存很不错，正版实体卡带，插卡即玩，支持所有Switch主机，动作冒险类神作，剧情丰富，开放世界探索，喜欢塞尔达系列的别错过～ 盒子和卡带都在，内容齐全，无划痕，无异常，读卡没问题，功能正常，放心入。 同城可自提，价格好说，喜欢直接拍，细节图私聊发～ | E65: 225 | F65: 郑习惯的电玩小店 | G65: 广东 | H65: https://www.goofish.com/item/1060681771343
A66: 2026-07-06 21:01:36 | B66: 塞尔达传说：王国之泪 | C66: 卡带 | D66: 个人闲置Switch《塞尔达传说：王国之泪》港版中文卡带，几 乎全新，带原装盒，保存很好，没啥明显使用痕迹。插卡即玩，支持所有Switch主机，国行、日版、港版都能用，正版保证，动作冒险类，探索乐趣多，喜欢塞尔达系列的别错过！ 不包邮，不退不换，介意勿拍。喜欢直接拍，细节图私聊发～ | E66: 230 | F66: 更努力皮皮虾蕊琪 | G66: 湖南 | H66: https://www.goofish.com/item/1064106709677
A67: 2026-07-06 21:01:36 | B67: 塞尔达传说：王国之泪 | C67: 卡带 | D67: 已下架 感兴趣的话点“我想要”和我私聊吧～ | E67: 355 | F67: 我是小烟头 | G67: 广东 | H67: https://www.goofish.com/item/1060563649975
A68: 2026-07-06 21:01:36 | B68: 塞尔达传说：王国之泪 | C68: 卡带 | D68: Switch塞尔达王国之泪 港版中文卡带，带盒，正版，插卡即 玩。 | E68: 260 | F68: 陈以根号二 | G68: 江苏 | H68: https://www.goofish.com/item/1057885576739
A69: 2026-07-06 21:01:36 | B69: 塞尔达传说：王国之泪 | C69: 卡带 | D69: 塞尔达传说王国之泪港版中文 任天堂Switch游戏《塞尔达传说：王国之泪》港版中文实体卡带，带原装盒，卡带表面干净，金手指无明显氧化，功能正常，支持所有Switch主机。 | E69: 250 | F69: 冥王星知足的荠菜 | G69: 宁夏 | H69: https://www.goofish.com/item/1046727565964
A70: 2026-07-06 21:01:36 | B70: 塞尔达传说：王国之泪 | C70: 卡带 | D70: 塞尔达传说 王国之泪 Switch港版实体卡带，中文，支持所 有Switch主机，国行/非国行都能用。带原装盒，成色几乎全新，盘面无划痕，功能正常，插卡即玩。适合喜欢开放世界动作冒险的玩家，收藏自用都合适。 温馨提示： 1、支持自提，南昌本地可约 2、售出不退不换 3、喜欢直接拍 | E70: 239 | F70: 桃桃子 | G70: 江西 | H70: https://www.goofish.com/item/1047331365265
A71: 2026-07-06 21:01:36 | B71: 塞尔达传说：王国之泪 | C71: 卡带 | D71: 99新！Switch 塞尔达传说 王国之泪 港版中文卡带，带 原装盒子，保存很好，正版卡带，插上即玩～ 支持中文 包邮，同城可自提 喜欢直接拍，细节私聊 正品保证！ 不刀！！ | E71: 250 | F71: 硬核研究所 | G71: 北京 | H71: https://www.goofish.com/item/1054763649487
A72: 2026-07-06 21:01:36 | B72: 塞尔达传说：王国之泪 | C72: 卡带 | D72: 99新 塞尔达传说王国之泪实体典藏版（无游戏卡带） 官方正品 只拆封看过 保存很新 包装有点小磨痕 喜欢直接拍 细节私聊～ | E72: 258 | F72: TianCan | G72: 广东 | H72: https://www.goofish.com/item/1054852779457
A73: 2026-07-06 21:01:36 | B73: 塞尔达传说：王国之泪 | C73: 卡带 | D73: Switch 塞尔达传说：王国之泪 自用闲置，带原装盒，卡带保存很好，只使用过两次，几乎全新 售出不退 | E73: 257 | F73: Leo电子工作室 | G73: 江苏 | H73: https://www.goofish.com/item/1039650090036
A74: 2026-07-06 21:01:36 | B74: 塞尔达传说：王国之泪 | C74: 卡带 | D74: 魂斗罗：加鲁加行动，塞尔达王国之泪，蕉力全开，马里奥赛车世界 ，都是全新未拆封 一口价，不包邮，买几张都是不砍价不包邮。 优先出打包的 | E74: 200 | F74: 泡芙喵喵? | G74: 江苏 | H74: https://www.goofish.com/item/1064506008279
... A97: 2026-07-06 21:01:36 | B97: 塞尔达传说：王国之泪 | C97: 卡带 | D97: 几乎全新Switch《塞尔达传说：王国之泪》欧版卡带，型号H AC-008 AXN7A09A000，正版实体，盘面干净，金手指状态很好，插卡即玩，支持所有Switch主机，动作冒险类，剧情丰富，玩法多样，喜欢塞尔达系列的别错过～ 只有卡带，无盒子，内容齐全，无划痕，无异常，读卡没问题，功能正常，收藏补坑都合适。 同城可自提，价格好说，喜欢直接拍，细节图私聊发～ | E97: 223 | F97: 郑习惯的电玩小店 | G97: 广东 | H97: https://www.goofish.com/item/1059602257662
A98: 2026-07-06 21:01:36 | B98: 塞尔达传说：王国之泪 | C98: 卡带 | D98: 塞尔达传说王国之泪游戏卡带 Switch平台游戏《塞尔达传说 王国之泪》实体卡带，屏幕显示游戏主界面，卡带外壳为黑色带浮雕纹饰边框，已通电可正常启动。 | E98: 75 | G98: 湖北 | H98: https://www.goofish.com/item/1049112401030
A99: 2026-07-06 21:01:36 | B99: 塞尔达传说：王国之泪 | C99: 卡带 | D99: Switch一代，塞尔达传说王国之泪游戏卡带，实体店入手，一 手自用成色充新，就玩了一次通关，闲置出，贩子勿扰，沈阳本地自提优先，外地爽快的包邮非偏远。 | E99: 238 | F99: Kevinkong_cn | G99: 辽宁 | H99: https://www.goofish.com/item/1063415093652
A100: 2026-07-06 21:01:36 | B100: 塞尔达传说：王国之泪 | C100: 卡带 | D100: 任天堂Switch 塞尔达传说 王国之泪 港版中文 几乎全新，带原装盒，卡带保存很好 正版卡带，读卡正常，插上即玩 包邮，可自提 不议价 | E100: 220 | F100: 半岛托腮的探花 | G100: 黑龙江 | H100: https://www.goofish.com/item/1064701212114
A101: 2026-07-06 21:01:36 | B101: 塞尔达传说：王国之泪 | C101: 卡带 | D101: 塞尔达传说王国之泪港版中文 任天堂Switch游戏《塞尔达传说：王国之泪》港版中文实体卡带，带原装盒，卡带外观干净，功能正常，支持所有Switch主机。 | E101: 245 | F101: 破忒头1 | G101: 四川 | H101: https://www.goofish.com/item/1049118792006
A102: 2026-07-06 21:01:36 | B102: 塞尔达传说：王国之泪 | C102: 卡带 | D102: 塞尔达传说王国之泪Switch卡带 日版《塞尔达传说：王国之泪》Switch实体游戏卡带，封面显示CERO B评级和日文标题，确认为官方正版。当前仅提供封面图，实物卡带、原包装盒、说明书及成色情况待确认。 | E102: 248 | F102: tbNick_4yfem | G102: 内蒙古 | H102: https://www.goofish.com/item/1033567399406
A103: 2026-07-06 21:01:36 | B103: 塞尔达传说：王国之泪 | C103: 卡带 | D103: 塞尔达王国之泪，Switch游戏卡带，全新日版，带原包装盒， 支持中文，插卡即玩，动作冒险开放世界，剧情超精彩！ 包邮发货，喜欢可以直接拍哦～ | E103: 277 | F103: 伊丽莎圆 | G103: 四川 | H103: https://www.goofish.com/item/1050145366617
A104: 2026-07-06 21:01:36 | B104: 塞尔达传说：王国之泪 | C104: 卡带 | D104: 塞尔达传说王国之泪 Switch卡带 成色几乎全新，带原装盒，卡带保存很好，插拔次数少，读卡正常 支持所有Switch主机，中文版，插卡即玩 包邮，可自提 喜欢的朋友可以私聊 | E104: 230 | F104: 平平安安 | G104: 天津 | H104: https://www.goofish.com/item/1057305966532
A105: 2026-07-06 21:01:36 | B105: 塞尔达传说：王国之泪 | C105: 卡带 | D105: 几乎全新 任天堂switch塞尔达王国之泪中文卡带 保存很好 没啥使用痕迹 适合喜欢塞尔达的玩家 支持自提 也可以邮寄 邮费zz 价格可聊 细节图私聊发 喜欢直接拍～ | E105: 261 | F105: 锡都理财的纸鳐 | G105: 安徽 | H105: https://www.goofish.com/item/1059236108816
A106: 2026-07-06 21:01:36 | B106: 塞尔达传说：王国之泪 | C106: 卡带 | D106: 【包邮】塞尔达传说：王国之泪 Switch卡带 日版中文，带原装盒，仅拔插过几次；插卡即玩 正版卡带，支持所有Switch主机 标价包邮 | E106: 229 | F106: 故作轻松的轻松熊 | G106: 山东 | H106: https://www.goofish.com/item/1061314722545
A107: 2026-07-06 21:01:36 | B107: 塞尔达传说：王国之泪 | C107: 卡带 | D107: Switch 塞尔达传说 王国之泪 带原装盒，不刀，包邮，售出不退不换，无售后。 | E107: 225 | F107: 渣还是那个渣 | G107: 江苏 | H107: https://www.goofish.com/item/1061980053042
A108: 2026-07-06 21:01:36 | B108: 塞尔达传说：王国之泪 | C108: 卡带 | D108: Switch《塞尔达传说：王国之泪》港版中文卡带，带原装盒， 盒子卡带都在，简体中文界面，包邮。 | E108: 221 | F108: 南风几时回 | G108: 云南 | H108: https://www.goofish.com/item/1049958130833
A109: 2026-07-06 21:01:36 | B109: 塞尔达传说：王国之泪 | C109: 卡带 | D109: ns卡带，switch游戏，塞尔达传说智慧再现港版，带原装盒 ，成色挺好，插卡即玩。同城可自提。 | E109: 200 | F109: boblue1982 | G109: 山东 | H109: https://www.goofish.com/item/1041663395055
A110: 2026-07-06 21:01:36 | B110: 塞尔达传说：王国之泪 | C110: 卡带 | D110: 塞尔达传说：王国之泪 日版Switch卡带，带原装盒，有说明 书，准全新，卡带和盒子都很新，自己一手全新塑封实体卡买的，拔插不超过 5 次，适合收藏，功能正常，支持中文，插上即玩 包邮，支持自提，喜欢直接拍，细节私聊 | E110: 235 | F110: 小菜丸子 | G110: 福建 | H110: https://www.goofish.com/item/1060229649812
A111: 2026-07-06 21:01:36 | B111: 塞尔达传说：王国之泪 | C111: 卡带 | D111: xbox闲置Switch塞尔达传说：王国之泪 港版中文卡带 带原装盒 几乎全新 拆封没怎么用 读取正常 支持中文 动作冒险 经典系列 喜欢塞尔达的可以入 包邮 支持自提 价格可聊 要细节图私信 | E111: 230 | G111: 辽宁 | H111: https://www.goofish.com/item/1043018713076
A112: 2026-07-06 21:01:36 | B112: 塞尔达传说：王国之泪 | C112: 卡带 | D112: 【任天堂Switch塞尔达传说：王国之泪 港版卡带】 淘宝购入成色几乎全新，带原装盒，中文界面，支持所有Switch主机，国行也能用，插卡即玩，经典动作冒险，剧情和玩法都很棒，收藏自用都合适。 包邮，同城可自提。喜欢直接拍，细节图可私聊。 | E112: 234 | F112: 太乙路攒钱的藿香 | G112: 浙江 | H112: https://www.goofish.com/item/1048054668463
A113: 2026-07-06 21:01:36 | B113: 塞尔达传说：王国之泪 | C113: 卡带 | D113: 塞尔达传说王国之泪港版中文卡带 任天堂Switch游戏《塞尔达传说：王国之泪》港版中文实体卡带，带原装盒，卡带表面干净，金手指无氧化，插拔次数少，功能正常，支持简体中文界面。 | E113: 240 | F113: 用户_02769793 | G113: 湖北 | H113: https://www.goofish.com/item/1055831772393
A114: 2026-07-06 21:01:36 | B114: 塞尔达传说：王国之泪 | C114: 卡带 | D114: 出几乎全新任天堂Switch 塞尔达传说王国之泪 港版中文卡 带+原装盒子 支持所有Switch主机，国行也能用，带amiibo功能，支持在线联机，画面精美，玩法丰富，经典动作冒险，适合收藏和日常娱乐！ 卡带和盒子保存很好，几乎没用过，成色看图吧 包邮，支持自提，售出不退不换！ 有实体店，本店还有其他... | E114: 255 | F114: 神鬼寓言 | G114: 河北 | H114: https://www.goofish.com/item/1012735404387
A115: 2026-07-06 21:01:36 | B115: 塞尔达传说：王国之泪 | C115: 卡带 | D115: Switch游戏卡带，塞尔达传说：王国之泪，美版，带原装盒， 盘面干净，成色几乎全新，正版保证，支持所有Switch主机，插上即玩，动作冒险经典，喜欢塞尔达系列的别错过！ 包邮，不议价，喜欢直接拍，细节私聊～ 售出不退不换 | E115: 226 | F115: 是a宇啊 | G115: 吉林 | H115: https://www.goofish.com/item/1048534398915
A116: 2026-07-06 21:01:36 | B116: 塞尔达传说：王国之泪 | C116: 卡带 | D116: 【南京无双电玩】全新ns《塞尔达传说王国之泪》，二手荒野之息 ➕大师之剑DLC 如题， 全新未拆王国之泪 295 二手荒野之息255 二手荒野之息➕DLC已出 南京实体店可自提 本店长期回收各种游戏机，正版游戏 本交易仅支持自提、当面交易、邮寄 | E116: 285 | F116: 南京无双电玩 | G116: 江苏 | H116: https://www.goofish.com/item/820770997830
A117: 2026-07-06 21:01:36 | B117: 塞尔达传说：王国之泪 | C117: 卡带 | D117: 马里奥赛车8 190 马里奥派对无盒 185 舞力全开2020 75 舞力全开2021 65 塞尔达旷野之息 210（已出） 塞尔达王国之泪 210（已出） 有盒，成色还行 要哪几个直接说 不包邮，可自提 不刀，不急慢出，所以不用来在问价格了 | E117: 190 | F117: 菜鸡鱼苗 | G117: 浙江 | H117: https://www.goofish.com/item/1058775929635
A118: 2026-07-06 21:01:36 | B118: 塞尔达传说：王国之泪 | C118: 卡带 | D118: 塞尔达传说王国之泪Switch卡带 任天堂Switch游戏《塞尔达传说：王国之泪》港版中文实体卡带，带原装盒，卡带金手指无氧化，盘面干净，功能正常，插卡即玩，支持简体中文和全区Switch主机。 | E118: 240 | F118: 回收电子元件 | G118: 广东 | H118: https://www.goofish.com/item/1059787829681
A119: 2026-07-06 21:01:36 | B119: 塞尔达传说：王国之泪 | C119: 卡带 | D119: 塞尔达传说：王国之泪 港版中文卡带 全新未拆封 同城可自提 | E119: 260 | F119: gr顾千河 | G119: 广西 | H119: https://www.goofish.com/item/1060737122692
A120: 2026-07-06 21:01:36 | B120: 塞尔达传说：王国之泪 | C120: 卡带 | D120: 塞尔达传说王国之泪 典藏版 日版 Switch游戏，带原装铁盒、设定资料集、别针徽章、钢铁材质海报，注意‼️没有卡带 几乎全新，已拆封，保存很好，配件齐全 适合收藏或送人 包邮发货，不退不换 实物图刚刚拍 | E120: 290 | F120: 菓兒1314 | G120: 福建 | H120: https://www.goofish.com/item/1020298558229
A121: 2026-07-06 21:01:36 | B121: 塞尔达传说：王国之泪 | C121: 卡带 | D121: 塞尔达传说王国之泪港版中文卡带 任天堂Switch游戏《塞尔达传说：王国之泪》港版中文实体卡带，带原装盒，功能正常，支持简体中文，可通用于所有Switch主机。 | E121: 245 | F121: 暗紫的多形藻属 | G121: 上海 | H121: https://www.goofish.com/item/1045434571842
A122: 2026-07-06 21:01:36 | B122: 塞尔达传说：王国之泪 | C122: 卡带 | D122: Nintendo Switch《塞尔达传说：王国之泪》卡带 带原装盒 卡带成色几乎全新 插卡即玩 非偏远包邮 售出不退不换 | E122: 240 | F122: 小太阳七号 | G122: 上海 | H122: https://www.goofish.com/item/1062497614175
A123: 2026-07-06 21:01:36 | B123: 塞尔达传说：王国之泪 | C123: 卡带 | D123: 塞尔达传说王国之泪港版中文卡带 任天堂Switch游戏《塞尔达传说：王国之泪》港版中文实体卡带，带原装盒，卡带表面干净，金手指无氧化，插上即玩，功能正常。 | E123: 240 | G123: 广东 | H123: https://www.goofish.com/item/1058980431138
A124: 2026-07-06 21:01:36 | B124: 塞尔达传说：王国之泪 | C124: 卡带 | D124: 塞尔达传说 王国之泪 Switch卡带 几乎全新 带原装盒 卡带干净 插卡即玩 支持所有Switch主机 不议价 喜欢直接拍 | E124: 230 | F124: 你真系禄七 | G124: 广东 | H124: https://www.goofish.com/item/1060688035221
A125: 2026-07-06 21:01:36 | B125: 塞尔达传说：王国之泪 | C125: 卡带 | D125: 塞尔达传说王国之泪Switch港版中文卡带 任天堂Switch游戏《塞尔达传说：王国之泪》港版中文实体卡带，带原装盒，功能正常，插拔次数少，保存良好。 | E125: 245 | F125: 我是艺艺子 | G125: 浙江 | H125: https://www.goofish.com/item/1059426881186
A126: 2026-07-06 21:01:36 | B126: 塞尔达传说：王国之泪 | C126: 卡带 | D126: 塞尔达传说王国之泪 塞尔达传说王国之泪，任天堂Switch游戏卡带，港版中文实体卡带，有原包装盒，支持所有Switch主机使用，正版游戏内容完整。 | E126: 249 | F126: 次年春序 | G126: 山东 | H126: https://www.goofish.com/item/1036900415869
A127: 2026-07-06 21:01:36 | B127: 塞尔达传说：王国之泪 | C127: 卡带 | D127: Nintendo Switch游戏卡带《塞尔达传说 王国之泪 》 港版中文，支持所有Switch主机， 卡带保存很好，几乎全新，带原包装盒 动作冒险经典，画面精美，玩法丰富 包邮，可自提，售出不退不换，喜欢的朋友私聊～ | E127: 240 | F127: 赛睿精品专卖 | G127: 浙江 | H127: https://www.goofish.com/item/1033899885352
A128: 2026-07-06 21:01:36 | B128: 塞尔达传说：王国之泪 | C128: 卡带 | D128: 塞尔达传说王国之泪，Switch卡带，带原装盒，中文版，成色 几乎全新，保存很好，卡带插拔次数极少，功能正常 230包邮，可自提 喜欢直接拍，细节私聊 | E128: 230 | F128: 能吃的小猪Rong | G128: 河北 | H128: https://www.goofish.com/item/1058357131373
A129: 2026-07-06 21:01:36 | B129: 塞尔达传说：王国之泪 | C129: 卡带 | D129: 任天堂明星大乱斗Switch卡带 港版 有盒，仅拔插一次，几乎全新 正版，支持Switch主机 包邮，喜欢直接拍，细节私聊～ | E129: 210 | F129: dawn拾玖 | G129: 江苏 | H129: https://www.goofish.com/item/1062515760992
A130: 2026-07-06 21:01:36 | B130: 塞尔达传说：王国之泪 | C130: 卡带 | D130: Switch 塞尔达传说 王国之泪 港版中文 原装盒装，正版实体卡带，插卡即玩，动作冒险类，玩法丰富，适合喜欢塞尔达系列的玩家。 非偏远地区包邮，价格已经很低，请勿议价，谢谢！ | E130: 246 | F130: 瑞克五代 | G130: 安徽 | H130: https://www.goofish.com/item/1054055715086
A131: 2026-07-06 21:01:36 | B131: 塞尔达传说：王国之泪 | C131: 卡带 | D131: 出Switch《塞尔达传说 王国之泪》港版中文卡带，几乎全新 ，带原包装盒，卡带金币已领，读取正常，插拔次数很少，保存很好 新鲜出炉的还热着不想玩了换设备，冲动购入结果没怎么玩，闲置出 支持简体中文，所有Switch主机都能用 包邮，可自提，不退不换，信用优先，喜欢直接拍，细节私聊 | E131: 278 | G131: 北京 | H131: https://www.goofish.com/item/1007176092264
A132: 2026-07-06 21:01:36 | B132: 塞尔达传说：王国之泪 | C132: 卡带 | D132: 【出】塞尔达旷野之息/王国之泪 Switch卡带 235一个，460两个，可单出可打包 不议价，讲价不回 | E132: 235 | F132: 威斯特彗星 | G132: 黑龙江 | H132: https://www.goofish.com/item/1054675329494
A133: 2026-07-06 21:01:36 | B133: 塞尔达传说：王国之泪 | C133: 卡带 | D133: 塞尔达旷野之息+王国之泪，卡带，带原装盒，插卡即玩，支持中文 。成色还可以，盒子卡带都在，功能正常。二手物品不退不换。自提可以优惠 | E133: 450 | F133: 星星的某某某 | G133: 湖北 | H133: https://www.goofish.com/item/1058877299199
A134: 2026-07-06 21:01:36 | B134: 塞尔达传说：王国之泪 | C134: 卡带 | D134: Switch 塞尔达传说 王国之泪 港版中文卡带，带原装盒， 几乎全新，卡带保存很好，插卡即玩，支持线下自提，支持国行/日版/港版Switch主机，全区中文，动作冒险神作，通关回血出，喜欢塞尔达系列别错过～支持线下自提 | E134: 235 | F134: 化城细致的瓜子 | G134: 广东 | H134: https://www.goofish.com/item/1060035708086
A135: 2026-07-06 21:01:36 | B135: 塞尔达传说：王国之泪 | C135: 卡带 | D135: 任天堂Switch游戏卡带 塞尔达传说：王国之泪 港版中文 港版中文实体卡带，带原装包装盒，封面印刷清晰，边角无明显磨损，手持状态显示保存良好，功能正常。 | E135: 245 | F135: 札幌好看的黑虎虾 | G135: 湖北 | H135: https://www.goofish.com/item/1039197387538
A136: 2026-07-06 21:01:36 | B136: 塞尔达传说：王国之泪 | C136: 卡带 | D136: 塞尔达传说：王国之泪 Switch卡带，欧版，带原装盒，成色 几乎全新，插卡即玩，支持中文，正版实体，动作冒险经典，剧情玩法都很棒，喜欢塞尔达系列的可以入。包邮，支持自提。 | E136: 225 | F136: 川三yoho | G136: 重庆 | H136: https://www.goofish.com/item/1057200019130
A137: 2026-07-06 21:01:36 | B137: 塞尔达传说：王国之泪 | C137: 卡带 | D137: 塞尔达传说王国之泪Switch卡带任天堂Switch游戏《塞 尔达传说：王国之泪》港版实体卡带，带原装盒，支持中文，卡带外观干净，金手指无明显氧化，功能正常，可通用于所有Switch主机。 | E137: 222 | F137: 小张的梦境 | G137: 四川 | H137: https://www.goofish.com/item/1057163854266
A138: 2026-07-06 21:01:36 | B138: 塞尔达传说：王国之泪 | C138: 卡带 | D138: 塞尔达王国之泪 switch游戏卡带 刚出的时候就买了，一手 换二代了 大刀勿扰 | E138: 237 | F138: 小羊爱吃大花菜 | G138: 陕西 | H138: https://www.goofish.com/item/1057815967060
A139: 2026-07-06 21:01:36 | B139: 塞尔达传说：王国之泪 | C139: 卡带 | D139: 【Switch游戏卡带】塞尔达传说 旷野之息 日版+美版，全 新未拆封，带原装盒，正版实体卡带，支持中文，插卡即玩，经典动作冒险，画面棒，收藏自用都合适！ 包邮，同城可自提，喜欢直接拍，细节私聊～标价是单个价格 | E139: 260 | F139: zedddd | G139: 河北 | H139: https://www.goofish.com/item/1059465759598
A140: 2026-07-06 21:01:36 | B140: 塞尔达传说：王国之泪 | C140: 卡带 | D140: 塞尔达传说王国之泪Switch卡带，欧版中文，带原装盒，卡带 +盒子都在，成色几乎全新，保存很好，功能正常，插卡即玩，支持所有Switch主机，读取没问题 自用闲置，回血出，本地可自提 | E140: 220 | F140: Trojan@ | G140: 山东 | H140: https://www.goofish.com/item/1051863730329
A141: 2026-07-06 21:01:36 | B141: 塞尔达传说：王国之泪 | C141: 卡带 | D141: 出Switch游戏卡带，塞尔达传说王国之泪，支持中文，插卡即 玩，成色还可以，金手指正常，插拔有点划痕，盘面干净，带一个ambin 刷卡器，前期摸索无忧！！个人闲置，喜欢的可以聊聊，价格可谈，二手物品不退 | E141: 226 | F141: 哇来次购 | G141: 浙江 | H141: https://www.goofish.com/item/1061931926631
A142: 2026-07-06 21:01:36 | B142: 塞尔达传说：王国之泪 | C142: 卡带 | D142: 塞尔达旷野之息 带原装盒，卡带干净，插拔次数少，支持中文，功 能正常，读卡没问题，盒子保存很好，收藏补坑都合适～ 江浙沪包邮，最好温州自提 | E142: 230 | F142: TB_20337468 | G142: 浙江 | H142: https://www.goofish.com/item/1054915201659
A143: 2026-07-06 21:01:36 | B143: 塞尔达传说：王国之泪 | C143: 卡带 | D143: switch塞尔达 王国之泪 实体卡 不议价 包装盒在 版本我不记得了 我不想研究了 你们自己看盒子吧 我是日版机器反正能玩有中文 非质量问题不退不换 | E143: 220 | F143: 肉都长在肚子上 | G143: 浙江 | H143: https://www.goofish.com/item/1050011619097
... A169: 2026-07-06 21:01:58 | B169: 塞尔达传说：旷野之息 | C169: 卡带 | D169: 塞尔达传说旷野之息 任天堂实体卡带 Switch ns 游戏 卡带，没盒子，有中文，可以用没任何问题。包邮普通快递。议价拉黑。 | E169: 210 | F169: 江城萌萌哒番茄 | G169: 安徽 | H169: https://www.goofish.com/item/1059394541756
A170: 2026-07-06 21:01:58 | B170: 塞尔达传说：旷野之息 | C170: 卡带 | D170: 插拔个位数，功能正常，日版，支持中文 超级马里奥赛车8 赛车送一个图二， 塞尔达旷野之息 马里奥空前盛会 马里奥惊奇 两件包邮，细节图私聊 | E170: 230 | G170: 江苏 | H170: https://www.goofish.com/item/1063547158838
A171: 2026-07-06 21:01:58 | B171: 塞尔达传说：旷野之息 | C171: 卡带 | D171: 塞尔达传说旷野之息Switch卡带 任天堂Switch游戏《塞尔达传说：旷野之息》实体卡带，带原装盒，支持中文，插卡即玩。卡带外观干净，金手指无明显氧化，盒子封面完整，整体保存较好。 | E171: 235 | F171: Cashmerewww | G171: 上海 | H171: https://www.goofish.com/item/1064497929138
A172: 2026-07-06 21:01:58 | B172: 塞尔达传说：旷野之息 | C172: 卡带 | D172: 任天堂Switch《塞尔达传说：旷野之息》美版卡带+《塞尔达 传说：王国之泪》港版卡带，卡带金手指干净，小纸片齐全，通关后就放起来了，只打包一起出，包邮，同城可自提。拒绝贩子，拒绝到手刀，喜欢直接拍，细节私聊～ | E172: 410 | F172: nelly哥 | G172: 北京 | H172: https://www.goofish.com/item/1060291999548
A173: 2026-07-06 21:01:58 | B173: 塞尔达传说：旷野之息 | C173: 卡带 | D173: 几乎全新Switch塞尔达旷野之息卡带，带原装盒，盒子保存很 好，插卡即玩，支持中文，读卡正常，功能都正常，没怎么用，具体看图。包邮，武汉可自提，喜欢直接拍或者私聊，细节随时问我～ | E173: 288 | F173: 喔喔er笑笑 | G173: 湖北 | H173: https://www.goofish.com/item/1062752531214
A174: 2026-07-06 21:01:58 | B174: 塞尔达传说：旷野之息 | C174: 卡带 | D174: 塞尔达传说 旷野之息 Switch 港版中文卡带，几乎全新， 带原装盒，卡带保存很好，插卡即玩，支持所有Switch主机，读卡正常，功能完好。适合自用或收藏，包邮。 | E174: 238 | F174: 反复无常的豆丁 | G174: 广东 | H174: https://www.goofish.com/item/1055040551627
A175: 2026-07-06 21:01:58 | B175: 塞尔达传说：旷野之息 | C175: 卡带 | D175: 包邮【Switch游戏卡带】异度锁链，ASTRAL CHAI N，日版，带壳，成色很好。包邮。 | E175: 156 | F175: 羊毛毛的开心果 | G175: 湖北 | H175: https://www.goofish.com/item/1036242668402
A176: 2026-07-06 21:01:58 | B176: 塞尔达传说：旷野之息 | C176: 卡带 | D176: 宝可梦Switch卡带，带原包装盒，动作冒险类 支持Switch主机，收藏or自用都很合适，官方正品，细节图可私聊发！ 宝可梦za无捆绑包，喜欢宝可梦系列的别错过啦～ ，支持验货，喜欢直接拍 | E176: 182 | F176: wllqxls | G176: 浙江 | H176: https://www.goofish.com/item/1044174026816
A177: 2026-07-06 21:01:58 | B177: 塞尔达传说：旷野之息 | C177: 卡带 | D177: 全新未拆封 Switch 汪汪队立大功1 巡逻队 Paw Patrol On A Roll 英文版 美版英文无中文，适合所有Switch主机，国行非国行机都能用 全新未拆封游戏 包邮便宜出 售出不退不换 | E177: 138 | F177: 春暖花开 | G177: 浙江 | H177: https://www.goofish.com/item/1037187339306
A178: 2026-07-06 21:01:58 | B178: 塞尔达传说：旷野之息 | C178: 卡带 | D178: 出售Switch游戏合集，包括塞尔达传说旷野之息250、健身 环大冒险260等热门游戏。几乎全新，所有游戏都带原装盒。 【出手理由】标价矿石镇价格 游戏收藏整理，闲置出，成色很好，适合Switch玩家收藏，价格不一样买前咨询。一起买500元 【售后说明】 二手游戏，售出不退不换，介意勿拍。 感兴趣的... | E178: 90 | F178: 背着月亮回你家 | G178: 北京 | H178: https://www.goofish.com/item/992116198785
A179: 2026-07-06 21:01:58 | B179: 塞尔达传说：旷野之息 | C179: 卡带 | D179: Switch 塞尔达旷野之息 中文版 带原装盒 盘面干净 读盘正常 支持所有Switch主机 国行/日版/港版/美版都能用 插卡即玩 成色还可以 有点使用痕迹 整体保存不错 正版卡带 金手指干净 没有明显磨损 包邮 北京可自提 喜欢直接拍 细节私聊 | E179: 238 | F179: 电玩北京实体店 | G179: 北京 | H179: https://www.goofish.com/item/1042052958676
A180: 2026-07-06 21:01:58 | B180: 塞尔达传说：旷野之息 | C180: 卡带 | D180: Switch MUSICUS 日版卡带 带原包装盒 成色几乎 全新 盘面干净 金手指完好 插卡即用 支持所有Switch主机 包邮 不退不换 | E180: 199 | F180: 沙滩甜甜的海豚螺 | G180: 福建 | H180: https://www.goofish.com/item/1050938488336
A181: 2026-07-06 21:01:58 | B181: 塞尔达传说：旷野之息 | C181: 卡带 | D181: 塞尔达传说 旷野之息 日版Switch游戏卡带 带冒险指南手册+地图 日版 支持中文 | E181: 264 | F181: Gero2 | G181: 辽宁 | H181: https://www.goofish.com/item/1055063234497
A182: 2026-07-06 21:01:58 | B182: 塞尔达传说：旷野之息 | C182: 卡带 | D182: Nintendo Switch 塞尔达传说 旷野之息 美版卡 带，带原包装盒，正版实体卡，插卡即玩，支持所有Switch主机，中文菜单，剧情经典，动作冒险类，适合喜欢探索的朋友～ 卡带和盒子都在，金手指干净，读卡正常，功能完好，收藏自用都合适！ 包邮，可自提，喜欢直接拍或私聊细节图～ 分类：Sw... | E182: 245 | F182: 新手铲屎官 | G182: 北京 | H182: https://www.goofish.com/item/1042042683996
... A200: 2026-07-06 21:01:58 | B200: 塞尔达传说：旷野之息 | C200: 卡带 | D200: 出全新卡带 未拆封 游戏清单 可议价 价格随意挂的 1. 茶杯头（Cuphead）：¥190 2. 刺客信条：逆命合集（重制版）：¥150 3. 空洞骑士（Hollow Knight）：¥210 4. 超级炸弹人R2：&yen... | E200: 150 | F200: 枫叶落乌肩 | G200: 江苏 | H200: https://www.goofish.com/item/1028894849387
A201: 2026-07-06 21:01:58 | B201: 塞尔达传说：旷野之息 | C201: 卡带 | D201: 99新switch塞尔达旷野之息卡带，带原装盒，插卡即玩，中 文界面，支持所有Switch主机，正版卡带，功能一切正常～ 平时用得很少，成色特别好，包邮发货！支持自提，喜欢直接拍，细节图私聊发～ 售出不退不换，有问题随时问我哈！ | E201: 233 | G201: 北京 | H201: https://www.goofish.com/item/1064917276566
A202: 2026-07-06 21:01:58 | B202: 塞尔达传说：旷野之息 | C202: 卡带 | D202: 任天堂Switch正版游戏 海贼王：时光旅诗 豪华版 港版中 文 带原装盒 卡带正常 支持所有Switch主机 包含DLC 成色几乎全新 发货前视频确认检查拒绝任何理由到手刀 | E202: 300 | F202: 就是玩儿? | G202: 吉林 | H202: https://www.goofish.com/item/1040582923950
A203: 2026-07-06 21:01:58 | B203: 塞尔达传说：旷野之息 | C203: 卡带 | D203: 塞尔达旷野之息日版卡带，带原装壳，成色如图，保存很好，读写正 常 江浙沪包邮，喜欢直接拍，细节私聊 | E203: 228 | F203: HaidyFly | G203: 浙江 | H203: https://www.goofish.com/item/1061213159011
A204: 2026-07-06 21:01:58 | B204: 塞尔达传说：旷野之息 | C204: 卡带 | D204: Switch游戏卡带《潜水员戴夫》周年纪念版，日版中文，带原 装盒，全新未拆封，塑封还在，保存很新，插卡即玩，支持所有Switch主机，电视和掌机模式都能用，正版实体卡，内容完整，功能正常。 【全新未拆封】日版 潜水员戴夫 周年纪念版 Switch卡带 日版中文 支持Switch主机 插卡即玩 正版实体卡 带原装盒 包装完整 休闲冒险必备 收藏自用都合适 包邮 支持自提 售出不退不换 喜欢直接拍 | E204: 147 | F204: in翠sing | G204: 山西 | H204: https://www.goofish.com/item/1061056579226
A205: 2026-07-06 21:01:58 | B205: 塞尔达传说：旷野之息 | C205: 卡带 | D205: 塞尔达旷野之息SN2，二代卡，全新未拆封，港版中文，支持中文 界面，插卡即玩，动作冒险经典，剧情丰富，适合喜欢塞尔达和动作游戏的朋友！非偏远地区包邮出，郑州地区可以自提 | E205: 310 | F205: 冰妮儿521 | G205: 河南 | H205: https://www.goofish.com/item/1064570373522
A206: 2026-07-06 21:01:58 | B206: 塞尔达传说：旷野之息 | C206: 卡带 | D206: 全新未拆封 日版 任天堂 Switch 星跃狂飙 星际冲板 未开封 正版卡带 带原包装盒 支持中文 动作冒险类游戏 开放世界体验 滑板战斗+解谜 | E206: 125 | F206: 小羊爱吃草 | G206: 贵州 | H206: https://www.goofish.com/item/1018711461147
A207: 2026-07-06 21:01:58 | B207: 塞尔达传说：旷野之息 | C207: 卡带 | D207: 【全新】塞尔达王国之泪 美版典藏铁盒，铁盒保存很好，套自封袋 ，目测无划痕。收藏向，适合喜欢塞尔达的朋友。不含游戏卡带，只有铁盒。 签收后如有问题以完整开箱视频为证，无视频不售后，不完整不售后。无问题不退换。 | E207: 55 | F207: Evol | G207: 山东 | H207: https://www.goofish.com/item/1031234968394
A208: 2026-07-06 21:01:58 | B208: 塞尔达传说：旷野之息 | C208: 卡带 | D208: 【出闲置】Switch 块魂 安可 日版卡带，带原包装盒，成 色很棒，基本没怎么玩，盒子也一直好好保存着，功能一切正常，读卡没问题，运行流畅～ 18年11月在tb买的的，原价一百八十多，现在闲置出掉，喜欢直接拍，包邮！支持自提，价格可聊，细节图私聊发～ | E208: 90 | F208: UP菌 | G208: 海南 | H208: https://www.goofish.com/item/1054466575656
A209: 2026-07-06 21:01:58 | B209: 塞尔达传说：旷野之息 | C209: 卡带 | D209: 塞尔达传说旷野之息Switch卡带 美版中文 LA-HAAA AA-USA HAC-008型号，黑色外壳，金手指触点干净，插拔正常，所见即所得 有原装盒，成色几乎全新，保存很好 所有Switch主机通用，支持联机，分级ESRB E级 自提减10 不退不换，不因成色问题退货 喜欢直接拍，细节私聊 | E209: 210 | F209: 刘小小蒙 | G209: 山东 | H209: https://www.goofish.com/item/1054646713596
A210: 2026-07-06 21:01:58 | B210: 塞尔达传说：旷野之息 | C210: 卡带 | D210: Switch游戏卡带 我的世界基岩版 日版中文 王舍人附近可 自取 全新未拆封 | E210: 180 | F210: 丰盛ii | G210: 山东 | H210: https://www.goofish.com/item/1044820921184
A211: 2026-07-06 21:01:58 | B211: 塞尔达传说：旷野之息 | C211: 卡带 | D211: 塞尔达传说旷野之息游戏本体，二手原装卡带带盒，成色不错，功能 正常，适合Switch主机，包邮，喜欢直接拍，细节私聊～ | E211: 240 | F211: 我爱崽崽们 | G211: 江苏 | H211: https://www.goofish.com/item/1063638096481
...

Sheet 价格历史
A1: 抓取日期 | B1: 抓取时间 | C1: 游戏名 | D1: 版本 | E1: 商品ID | F1: 商品标题 | G1: 价格 | H1: 卖家 | I1: 地区 | J1: 商品链接
A2: 2026-07-06 | B2: 2026-07-06 15:13:35 | C2: 塞尔达传说：王国之泪 | D2: 卡带 | E2: 1065071636384 | F2: Switch 塞尔达传说 王国之泪 中文卡带，插卡即玩，支持 中文，画面精美，玩法丰富，动作冒险经典，喜欢塞尔达的朋友别错过。卡带保存很好，功能正常，成色实图所拍，看准再下单，售出不退不换。非偏远地区包邮，偏远地区补差5元，售后需要提供完整开箱视频 | G2: 222 | H2: 广东卖家信用极好 | J2: https://www.goofish.com/item?id=1065071636384&categoryId=201538503
A3: 2026-07-06 | B3: 2026-07-06 15:13:35 | C3: 塞尔达传说：王国之泪 | D3: 卡带 | E3: 1062436555866 | F3: 现货！任天堂Switch《塞尔达传说：王国之泪》港版中文卡带 ，支持所有Switch主机，插卡即玩。正版实体卡，带原包装盒，功能正常，成色几乎全新，保存很好，收藏自用都合适。动作冒险类，剧情丰富，画面精美，适合喜欢塞尔达系列的朋友。包邮 支持自提喜欢直接拍 细节私聊 | G3: 225 | H3: 北京卖家信用极好 | J3: https://www.goofish.com/item?id=1062436555866&categoryId=201538503
A4: 2026-07-06 | B4: 2026-07-06 15:13:35 | C4: 塞尔达传说：王国之泪 | D4: 卡带 | E4: 1063504494143 | F4: 塞尔达传说 呼吸之野 王者天下之泪 Switc 日本代购 塞尔达传说 呼吸之野 王者天下之泪 Switch【商品信息】已确认通电正常、各项功能可正常使用塞尔达传说旷野之息旷野之息（简称）王国之泪蒂亚金Nintendo Switch柔软实体版夏日开场礼上线啦！7.2-7.7 限时9折拍下后自动改价，等待改价成功后再付款哦由于海关备案规则调整，二手衣物类商品（适用范围：包含上衣、裤装、裙装、外套、童装 | G4: 512 | H4: 广东回复超快 | J4: https://www.goofish.com/item?id=1063504494143&categoryId=201538503
A5: 2026-07-06 | B5: 2026-07-06 15:13:35 | C5: 塞尔达传说：王国之泪 | D5: 卡带 | E5: 1063045721996 | F5: Switch《塞尔达传说：王国之泪》港版实体卡带 支持中文 带原包装盒正版实体卡 插卡即玩珠海现货 下午2点前付款当天发货 包邮不还价 还价勿扰售出不退 | G5: 239 | H5: 广东百分百好评 | J5: https://www.goofish.com/item?id=1063045721996&categoryId=201538503
A6: 2026-07-06 | B6: 2026-07-06 15:13:35 | C6: 塞尔达传说：王国之泪 | D6: 卡带 | E6: 1063894193418 | F6: Switch OLED游戏机贴纸 普通版/续航版贴纸塞 尔达传说王国之泪UCG特典全新未拆封，原包装在包邮非偏远喜欢直接拍，细节私聊 | H6: 江苏百分百好评 | J6: https://www.goofish.com/item?id=1063894193418&categoryId=201538503
A7: 2026-07-06 | B7: 2026-07-06 15:13:35 | C7: 塞尔达传说：王国之泪 | D7: 卡带 | E7: 1062839489790 | F7: 任天堂Switch游戏《塞尔达传说：王国之泪》港版中文卡带， 全新未拆封，带原装盒，支持简体中文，插卡即玩。动作冒险类，单人游戏，喜欢探索和开放世界的玩家别错过！同城可自提。不议价，售出不退。 | G7: 255 | H7: 吉林百分百好评 | J7: https://www.goofish.com/item?id=1062839489790&categoryId=201538503
A8: 2026-07-06 | B8: 2026-07-06 15:13:35 | C8: 塞尔达传说：王国之泪 | D8: 卡带 | E8: 1065444324578 | F8: Nintendo Switch 塞尔达传说：王国之泪 美版卡 带，带原包装盒，正版实体卡，插卡即玩，支持所有Switch主机（国行/港版/日版/欧美版都能用），动作冒险类，玩法自由，探索创造，amiibo兼容，聚会、朋友、家庭都适合，塞尔达系列粉丝必入～卡带和盒子保存很好，轻微划痕磨损，读卡正常，到手即玩！包邮，可自提，喜欢直接拍或私聊细节图～分类：Switch游戏卡带成色：轻微划痕磨损带原包装盒 | G8: 245 | H8: 北京回复超快 | J8: https://www.goofish.com/item?id=1065444324578&categoryId=201538503
A9: 2026-07-06 | B9: 2026-07-06 15:13:35 | C9: 塞尔达传说：王国之泪 | D9: 卡带 | E9: 1062527995032 | F9: Switch 塞尔达传说 王国之泪 中文插卡即玩，支持中文， 画面精美，动作冒险经典，喜欢塞尔达的朋友别错过。卡带保存很好，功能正常，成色实图所拍，看准再下单，售出不退不换。非偏远地区包邮，偏远地区补差5元，售后需要提供完整开箱视频 | G9: 222 | H9: 广东卖家信用极好 | J9: https://www.goofish.com/item?id=1062527995032&categoryId=201538503
A10: 2026-07-06 | B10: 2026-07-06 15:13:35 | C10: 塞尔达传说：王国之泪 | D10: 卡带 | E10: 1063229422642 | F10: 全新《塞尔达传说：王国之泪》港版中文卡带，带原装盒，插卡即玩 ，支持所有Switch主机，简体中文界面，动作冒险经典，剧情画质都很棒，喜欢塞尔达系列的朋友别错过！插拔次数很少，卡带表面很新没划痕，保存很好，功能正常，读取没问题，正版实体卡带，放心入！ | G10: 235 | H10: 吉林百分百好评 | J10: https://www.goofish.com/item?id=1063229422642&categoryId=201538503
A11: 2026-07-06 | B11: 2026-07-06 15:13:35 | C11: 塞尔达传说：王国之泪 | D11: 卡带 | E11: 1063921948905 | F11: 几乎全新 塞尔达传说 王国之泪 港版中文卡带 带原装盒，卡带保存很好，插拔次数很少，读卡正常，插卡即玩，支持所有Switch主机，动作冒险类，剧情画面都很棒，喜欢塞尔达的别错过～包邮发货，支持同城自提，价格可聊喜欢直接拍，细节随时问我！ | G11: 238 | H11: 江苏 | J11: https://www.goofish.com/item?id=1063921948905&categoryId=201538503
A12: 2026-07-06 | B12: 2026-07-06 15:13:35 | C12: 塞尔达传说：王国之泪 | D12: 卡带 | E12: 1063286182025 | F12: 全新未拆Switch 塞尔达传说王国之泪 港版中文实体卡带 带原包装盒 支持中文 插卡即玩南京发货 包邮 售出不退不换 | G12: 259 | H12: 江苏卖家信用极好 | J12: https://www.goofish.com/item?id=1063286182025&categoryId=201538503
A13: 2026-07-06 | B13: 2026-07-06 15:13:35 | C13: 塞尔达传说：王国之泪 | D13: 卡带 | E13: 1063322705883 | F13: 塞尔达传说王国之泪港版中文卡带任天堂Switch游戏《塞尔达 传说：王国之泪》港版中文实体卡带，带原装盒，卡带外观干净，插卡即玩，支持所有Switch主机。 | G13: 224 | H13: 上海百分百好评 | J13: https://www.goofish.com/item?id=1063322705883&categoryId=201538503
A14: 2026-07-06 | B14: 2026-07-06 15:13:35 | C14: 塞尔达传说：王国之泪 | D14: 卡带 | E14: 1062562059766 | F14: 全新Switch塞尔达传说:王国之泪，港版中文，首发版全新未 拆封，包含特典钥匙包。包邮，不议价，议价不回。 | G14: 255 | H14: 湖北百分百好评 | J14: https://www.goofish.com/item?id=1062562059766&categoryId=201538503
A15: 2026-07-06 | B15: 2026-07-06 15:13:35 | C15: 塞尔达传说：王国之泪 | D15: 卡带 | E15: 1063131326714 | F15: 塞尔达传说 王国之泪 Switch卡带支持中文 带原装盒 成色几乎全新 外观很新 没啥痕迹插拔次数少 卡带干净 | G15: 220 | H15: 河北卖家信用极好 | J15: https://www.goofish.com/item?id=1063131326714&categoryId=201538503
A16: 2026-07-06 | B16: 2026-07-06 15:13:35 | C16: 塞尔达传说：王国之泪 | D16: 卡带 | E16: 1064962448011 | F16: 塞尔达王国之泪 港版中文卡带，带原装盒，成色几乎全新，插卡即 玩，支持所有Switch主机，简体中文，动作冒险经典，剧情画面都很棒，适合自用或收藏，包邮杭州临平附近可自提，喜欢直接拍，细节私聊 | G16: 240 | H16: 浙江 | J16: https://www.goofish.com/item?id=1064962448011&categoryId=201538503
A17: 2026-07-06 | B17: 2026-07-06 15:13:35 | C17: 塞尔达传说：王国之泪 | D17: 卡带 | E17: 1062890417077 | F17: 全新《塞尔达传说：王国之泪》港版中文卡带，带原装盒，插卡即玩 ，支持所有Switch主机，简体中文界面，动作冒险经典，剧情画质都很棒，喜欢塞尔达系列的朋友别错过！插拔次数很少，卡带表面很新没划痕，保存很好，功能正常，读取没问题，正版实体卡带，放心入！同城可自提，喜欢直接拍，细节图私聊发～ | G17: 235 | H17: 吉林百分百好评 | J17: https://www.goofish.com/item?id=1062890417077&categoryId=201538503
A18: 2026-07-06 | B18: 2026-07-06 15:13:35 | C18: 塞尔达传说：王国之泪 | D18: 卡带 | E18: 1063118754379 | F18: switch塞尔达传说 王国之泪 中文卡带，插卡即玩，支持所 有Switch主机，日版也能用。卡带保存很好，盒子完整，功能正常，成色实图所拍，适合喜欢塞尔达系列和动作冒险游戏的朋友收藏或自用。二手卡带，功能正常，成色实图所拍，看准再下单，售出不退不换。非偏远地区包邮，偏远地区补差5元，售后需要提供完整开箱视频 | G18: 222 | H18: 广东卖家信用极好 | J18: https://www.goofish.com/item?id=1063118754379&categoryId=201538503
A19: 2026-07-06 | B19: 2026-07-06 15:13:35 | C19: 塞尔达传说：王国之泪 | D19: 卡带 | E19: 1064252533658 | F19: switch塞尔达ns王国之泪1.1.1版本 联机更新 非数 字版 非实体版 是正版！正版更新内容。但凡用高版本进过游戏都得格式化主机。 | H19: 广东百分百好评 | J19: https://www.goofish.com/item?id=1064252533658&categoryId=201538503
A20: 2026-07-06 | B20: 2026-07-06 15:13:35 | C20: 塞尔达传说：王国之泪 | D20: 卡带 | E20: 1064321009143 | F20: 《塞尔达传说 王国之泪》 switch 实体卡带回血 港版中文，成色很好，买来一直吃灰，真正的一手货（当时实体店买的全新的），带原装盒，盒子完整，喜欢直接拍二手物品售出不接受退货不刀，免开尊口爽快包顺丰 | G20: 225 | H20: 陕西百分百好评 | J20: https://www.goofish.com/item?id=1064321009143&categoryId=201538503
A21: 2026-07-06 | B21: 2026-07-06 15:13:35 | C21: 塞尔达传说：王国之泪 | D21: 卡带 | E21: 1062322094291 | F21: 塞尔达 繁体中文卡带 标准版 23年5月淘宝买的，原价三百多，没怎么玩，卡带保存不错，盒子也在默认顺丰到付 售出不退 | G21: 234 | H21: 广东发货极快 | J21: https://www.goofish.com/item?id=1062322094291&categoryId=201538503
A22: 2026-07-06 | B22: 2026-07-06 15:13:35 | C22: 塞尔达传说：王国之泪 | D22: 卡带 | E22: 1065422204334 | F22: 【出】任天堂switch1&2实体游戏卡带（塞尔达传说：旷野 之息、塞尔达传说：王国之泪、空洞骑士、宝可梦朱紫、宝可梦传说：阿尔宙斯、宝可梦传说：ZA）日版港版卡带，带原装盒（部分包含宣传卡），保存很好，插上就能玩，支持中文，动作冒险经典，收藏自用都合适。*包邮出，全程录像打包发货（收货售出后不退不换）需要可以联系私聊～一次多买打包更优惠 | G22: 240 | H22: 河南百分百好评 | J22: https://www.goofish.com/item?id=1065422204334&categoryId=201538503
A23: 2026-07-06 | B23: 2026-07-06 15:14:09 | C23: 塞尔达传说：旷野之息 | D23: 卡带 | E23: 1065071636384 | F23: Switch 塞尔达传说 王国之泪 中文卡带，插卡即玩，支持 中文，画面精美，玩法丰富，动作冒险经典，喜欢塞尔达的朋友别错过。卡带保存很好，功能正常，成色实图所拍，看准再下单，售出不退不换。非偏远地区包邮，偏远地区补差5元，售后需要提供完整开箱视频 | G23: 222 | H23: 广东卖家信用极好 | J23: https://www.goofish.com/item?id=1065071636384&categoryId=201538503
A24: 2026-07-06 | B24: 2026-07-06 15:14:09 | C24: 塞尔达传说：旷野之息 | D24: 卡带 | E24: 1062116315282 | F24: 任天堂Switch游戏卡带 塞尔达旷野之息 美版 几乎全新 带原装盒 支持中文界面 读卡正常 适合所有Switch主机 爽快包邮 | G24: 219 | H24: 广东 | J24: https://www.goofish.com/item?id=1062116315282&categoryId=201538503
A25: 2026-07-06 | B25: 2026-07-06 15:14:09 | C25: 塞尔达传说：旷野之息 | D25: 卡带 | E25: 1065061792450 | F25: Switch《塞尔达传说：旷野之息》卡带，带原装盒，美版，支 持中文，插拔次数少，卡带金手指状态好，盘面干净无划痕，盒子保存很好，适合所有Switch主机包邮！售出不退！ | G25: 215 | H25: 北京百分百好评 | J25: https://www.goofish.com/item?id=1065061792450&categoryId=201538503
A26: 2026-07-06 | B26: 2026-07-06 15:14:09 | C26: 塞尔达传说：旷野之息 | D26: 卡带 | E26: 1062696219271 | F26: 塞尔达传说旷野之息Switch卡带 美版实体卡带，支持中文，带原装盒，功能正常，适用于所有Switch主机（国行除外） | G26: 230 | H26: 湖北发货极快 | J26: https://www.goofish.com/item?id=1062696219271&categoryId=201538503
A27: 2026-07-06 | B27: 2026-07-06 15:14:09 | C27: 塞尔达传说：旷野之息 | D27: 卡带 | E27: 1063504494143 | F27: 塞尔达传说 呼吸之野 王者天下之泪 Switc 日本代购 塞尔达传说 呼吸之野 王者天下之泪 Switch【商品信息】已确认通电正常、各项功能可正常使用塞尔达传说旷野之息旷野之息（简称）王国之泪蒂亚金Nintendo Switch柔软实体版夏日开场礼上线啦！7.2-7.7 限时9折拍下后自动改价，等待改价成功后再付款哦由于海关备案规则调整，二手衣物类商品（适用范围：包含上衣、裤装、裙装、外套、童装 | G27: 512 | H27: 广东回复超快 | J27: https://www.goofish.com/item?id=1063504494143&categoryId=201538503
A28: 2026-07-06 | B28: 2026-07-06 15:14:09 | C28: 塞尔达传说：旷野之息 | D28: 卡带 | E28: 1061056579226 | F28: Switch游戏卡带《潜水员戴夫》周年纪念版，日版中文，带原 装盒，全新未拆封，塑封还在，保存很新，插卡即玩，支持所有Switch主机，电视和掌机模式都能用，正版实体卡，内容完整，功能正常。【全新未拆封】日版 潜水员戴夫 周年纪念版 Switch卡带日版中文 支持Switch主机 插卡即玩正版实体卡 带原装盒 包装完整休闲冒险必备 收藏自用都合适包邮 支持自提售出不退不换喜欢直接拍 | G28: 147 | H28: 山西卖家信用极好 | J28: https://www.goofish.com/item?id=1061056579226&categoryId=201538503
A29: 2026-07-06 | B29: 2026-07-06 15:14:09 | C29: 塞尔达传说：旷野之息 | D29: 卡带 | E29: 1062536275614 | F29: 全新未拆 日版NS《哈迪斯 HADES》卡带 带原装盒 支持Switch主机 插卡即玩动作RPG神作 支持中文 收藏自用都合适标价包邮 喜欢直拍 细节私聊 | G29: 120 | H29: 广东卖家信用极好 | J29: https://www.goofish.com/item?id=1062536275614&categoryId=201538503
A30: 2026-07-06 | B30: 2026-07-06 15:14:09 | C30: 塞尔达传说：旷野之息 | D30: 卡带 | E30: 1062527995032 | F30: Switch 塞尔达传说 王国之泪 中文插卡即玩，支持中文， 画面精美，动作冒险经典，喜欢塞尔达的朋友别错过。卡带保存很好，功能正常，成色实图所拍，看准再下单，售出不退不换。非偏远地区包邮，偏远地区补差5元，售后需要提供完整开箱视频 | G30: 222 | H30: 广东卖家信用极好 | J30: https://www.goofish.com/item?id=1062527995032&categoryId=201538503
A31: 2026-07-06 | B31: 2026-07-06 15:14:09 | C31: 塞尔达传说：旷野之息 | D31: 卡带 | E31: 1065444796068 | F31: 塞尔达传说 旷野之息 Switch 美版卡带，正版实体卡，插 卡即玩，支持中文，动作冒险类，开放世界玩法，朋友、家庭聚会都很适合，塞尔达粉必入～卡带成色轻微划痕磨损，金手指干净，读卡正常，到手即玩！包邮，可自提，喜欢直接拍或私聊细节图～分类：Switch游戏卡带成色：轻微划痕磨损美版卡带商品无质量问题，发出后不退不换。请拍摄完整开箱视频。 | G31: 229 | H31: 北京回复超快 | J31: https://www.goofish.com/item?id=1065444796068&categoryId=201538503
... A33: 2026-07-06 | B33: 2026-07-06 15:14:09 | C33: 塞尔达传说：旷野之息 | D33: 卡带 | E33: 1065023744561 | F33: Switch 塞尔达旷野之息 港版中文卡带，带原装盒子，插拔 次数只有一次，9.9新，买给人类小孩玩的说不喜欢就闲置了。原价297，现在230顺丰包邮。议价不回。支持所有Switch主机，国行可用，支持自提 | G33: 230 | H33: 福建百分百好评 | J33: https://www.goofish.com/item?id=1065023744561&categoryId=201538503
A34: 2026-07-06 | B34: 2026-07-06 15:14:09 | C34: 塞尔达传说：旷野之息 | D34: 卡带 | E34: 1063894193418 | F34: Switch OLED游戏机贴纸 普通版/续航版贴纸塞 尔达传说王国之泪UCG特典全新未拆封，原包装在包邮非偏远喜欢直接拍，细节私聊 | H34: 江苏百分百好评 | J34: https://www.goofish.com/item?id=1063894193418&categoryId=201538503
A35: 2026-07-06 | B35: 2026-07-06 15:14:09 | C35: 塞尔达传说：旷野之息 | D35: 卡带 | E35: 1063025990025 | F35: 任天堂switch 塞尔达传说 旷野之息 日版卡带 原装正品，带盒子，功能正常，插卡即玩支持所有Switch主机（日版/港版/国行都能用），开放世界动作冒险经典，画面很棒，适合喜欢塞尔达的玩家收藏或自用全国包邮，除偏远地区补运费不议价，喜欢直接拍，需要细节图可私聊NintendoSwitch 塞尔达旷野之息 | G35: 225 | H35: 浙江回复超快 | J35: https://www.goofish.com/item?id=1063025990025&categoryId=201538503
A36: 2026-07-06 | B36: 2026-07-06 15:14:09 | C36: 塞尔达传说：旷野之息 | D36: 卡带 | E36: 1062485279668 | F36: 几乎全新 塞尔达旷野之息 美版卡带 带原装盒 支持中文 读卡正常插上就能玩 经典神作 开放世界探索包邮 支持自提喜欢直接拍 细节私聊 | G36: 225 | H36: 天津卖家信用极好 | J36: https://www.goofish.com/item?id=1062485279668&categoryId=201538503
A37: 2026-07-06 | B37: 2026-07-06 15:14:09 | C37: 塞尔达传说：旷野之息 | D37: 卡带 | E37: 1062536483807 | F37: 全新未拆 Switch 路易吉鬼屋3 日版中文 标价包邮 喜欢直拍 细节私聊 | G37: 230 | H37: 广东卖家信用极好 | J37: https://www.goofish.com/item?id=1062536483807&categoryId=201538503
A38: 2026-07-06 | B38: 2026-07-06 15:14:09 | C38: 塞尔达传说：旷野之息 | D38: 卡带 | E38: 1061213159011 | F38: 塞尔达旷野之息日版卡带，带原装壳，成色如图，保存很好，读写正 常江浙沪包邮，喜欢直接拍，细节私聊 | G38: 228 | H38: 浙江百分百好评 | J38: https://www.goofish.com/item?id=1061213159011&categoryId=201538503
A39: 2026-07-06 | B39: 2026-07-06 15:14:09 | C39: 塞尔达传说：旷野之息 | D39: 卡带 | E39: 1063118754379 | F39: switch塞尔达传说 王国之泪 中文卡带，插卡即玩，支持所 有Switch主机，日版也能用。卡带保存很好，盒子完整，功能正常，成色实图所拍，适合喜欢塞尔达系列和动作冒险游戏的朋友收藏或自用。二手卡带，功能正常，成色实图所拍，看准再下单，售出不退不换。非偏远地区包邮，偏远地区补差5元，售后需要提供完整开箱视频 | G39: 222 | H39: 广东卖家信用极好 | J39: https://www.goofish.com/item?id=1063118754379&categoryId=201538503
A40: 2026-07-06 | B40: 2026-07-06 15:14:09 | C40: 塞尔达传说：旷野之息 | D40: 卡带 | E40: 1064497929138 | F40: 塞尔达传说旷野之息Switch卡带 任天堂Switch游戏《塞尔达传说：旷野之息》实体卡带，带原装盒，支持中文，插卡即玩。卡带外观干净，金手指无明显氧化，盒子封面完整，整体保存较好。 | G40: 235 | H40: 上海卖家信用优秀 | J40: https://www.goofish.com/item?id=1064497929138&categoryId=201538503
A41: 2026-07-06 | B41: 2026-07-06 15:14:09 | C41: 塞尔达传说：旷野之息 | D41: 卡带 | E41: 1063782517793 | F41: ⭕switch卡带 塞尔达旷野之息裸卡 ⭕任天堂正版，无盒，有中文⭕状态看图吧，标价包邮非偏远⭕喜欢直接拍，售出不退不换需要细节私聊，价格可聊 | G41: 231 | H41: 四川百分百好评 | J41: https://www.goofish.com/item?id=1063782517793&categoryId=201538503
A42: 2026-07-06 | B42: 2026-07-06 15:14:09 | C42: 塞尔达传说：旷野之息 | D42: 卡带 | E42: 1063922149086 | F42: Switch 塞尔达旷野之息 港版中文卡带 一手自玩，插拔次数较少，包邮，支持自提 | G42: 240 | H42: 北京百分百好评 | J42: https://www.goofish.com/item?id=1063922149086&categoryId=201538503
A43: 2026-07-06 | B43: 2026-07-06 15:14:09 | C43: 塞尔达传说：旷野之息 | D43: 卡带 | E43: 1062482782723 | F43: Switch 勇者斗恶龙3 HD-2D重制版 港版中文 几乎全新，带原装盒子和卡带支持所有Switch主机，中文界面包邮，不议价，售出不退 | G43: 188 | H43: 上海卖家信用极好 | J43: https://www.goofish.com/item?id=1062482782723&categoryId=201538503
A44: 2026-07-06 | B44: 2026-07-06 15:14:09 | C44: 塞尔达传说：旷野之息 | D44: 卡带 | E44: 1064917276566 | F44: 99新switch塞尔达旷野之息卡带，带原装盒，插卡即玩，中 文界面，支持所有Switch主机，正版卡带，功能一切正常～平时用得很少，成色特别好，包邮发货！支持自提，喜欢直接拍，细节图私聊发～售出不退不换，有问题随时问我哈！ | G44: 233 | H44: 北京卖家信用优秀 | J44: https://www.goofish.com/item?id=1064917276566&categoryId=201538503
A45: 2026-07-06 | B45: 2026-07-06 15:14:09 | C45: 塞尔达传说：旷野之息 | D45: 卡带 | E45: 1063286182025 | F45: 全新未拆Switch 塞尔达传说王国之泪 港版中文实体卡带 带原包装盒 支持中文 插卡即玩南京发货 包邮 售出不退不换 | G45: 259 | H45: 江苏卖家信用极好 | J45: https://www.goofish.com/item?id=1063286182025&categoryId=201538503
A46: 2026-07-06 | B46: 2026-07-06 15:14:09 | C46: 塞尔达传说：旷野之息 | D46: 卡带 | E46: 1063921948905 | F46: 几乎全新 塞尔达传说 王国之泪 港版中文卡带 带原装盒，卡带保存很好，插拔次数很少，读卡正常，插卡即玩，支持所有Switch主机，动作冒险类，剧情画面都很棒，喜欢塞尔达的别错过～包邮发货，支持同城自提，价格可聊喜欢直接拍，细节随时问我！ | G46: 238 | H46: 江苏 | J46: https://www.goofish.com/item?id=1063921948905&categoryId=201538503
... A85: 2026-07-06 | B85: 2026-07-06 15:15:12 | C85: 超级马力欧奥德赛 | D85: 卡带 | E85: 1065405472358 | F85: Switch 超级马里奥奥德赛 港版中文卡带 全新未拆封 带原包装盒支持Switch主机 插卡即玩 中文界面正版实体卡带 动作冒险类非偏远地区包邮售出不退不换 | G85: 225 | H85: 浙江百分百好评 | J85: https://www.goofish.com/item?id=1065405472358&categoryId=201538503
A86: 2026-07-06 | B86: 2026-07-06 15:15:12 | C86: 超级马力欧奥德赛 | D86: 卡带 | E86: 1063947916518 | F86: Switch 超级马里奥 酷霸王 amibo 国行版 带原装 盒 支持Switch主机 未拆封 非偏包邮 可自提 只和信用好的交易 | H86: 贵州百分百好评 | J86: https://www.goofish.com/item?id=1063947916518&categoryId=201538503
A87: 2026-07-06 | B87: 2026-07-06 15:15:12 | C87: 超级马力欧奥德赛 | D87: 卡带 | E87: 1064193005845 | F87: 全新！《超级马里奥 奥德赛》 港版卡带，带原装盒，正品保证，插卡即玩，支持所有Switch主机，中文界面，动作冒险经典，玩法丰富，适合马里奥粉丝和家庭聚会。包邮，深圳宝安/福田可自提。⚠️一旦售出不退不换！需要细节私聊。 | G87: 228 | H87: 广东百分百好评 | J87: https://www.goofish.com/item?id=1064193005845&categoryId=201538503
A88: 2026-07-06 | B88: 2026-07-06 15:15:12 | C88: 超级马力欧奥德赛 | D88: 卡带 | E88: 1065277904182 | F88: 全新Switch 超级马里奥奥德赛 港版中文卡带 带原包装盒 支持中文 插卡即玩包邮拍下不退 | G88: 230 | H88: 广东百分百好评 | J88: https://www.goofish.com/item?id=1065277904182&categoryId=201538503
A89: 2026-07-06 | B89: 2026-07-06 15:15:12 | C89: 超级马力欧奥德赛 | D89: 卡带 | E89: 1063505206722 | F89: 全国上门回收相机，镜头，摄影机，运动相机，大疆无人机，口袋相 机，运动相机，数码相机，单反相机，单反镜头等数码摄影器材，免费上门回收，外地谈好价格先打款再发货。上门直接拿！各类数码产品都可以回收！全国连锁实体店，诚信经营。高价上门回收佳能，尼康，索尼，富士，松下，奥林巴斯，徕卡，哈苏，相机数码，适马，腾龙，唯卓仕，相机镜头，摄像机，稳定器，运动相机 ，ccd卡片机，口袋相机，稳定器，大疆无人机，平 | H89: 天津 | J89: https://www.goofish.com/item?id=1063505206722&categoryId=201455413
A90: 2026-07-06 | B90: 2026-07-06 15:15:12 | C90: 超级马力欧奥德赛 | D90: 卡带 | E90: 1063502674756 | F90: 高价上门回收相机，镜头，摄影机，运动相机，大疆无人机，口袋相 机，运动相机，数码相机，单反相机，单反镜头等数码摄影器材，免费上门回收，外地谈好价格先打款再发货。上门直接拿！各类数码产品都可以回收！全国连锁实体店，诚信经营。高价上门回收佳能，尼康，索尼，富士，松下，奥林巴斯，徕卡，哈苏，相机数码，适马，腾龙，唯卓仕，相机镜头，摄像机，稳定器，运动相机 ，ccd卡片机，口袋相机，稳定器，大疆无人机，平 | H90: 西藏 | J90: https://www.goofish.com/item?id=1063502674756&categoryId=201455413
A91: 2026-07-06 | B91: 2026-07-06 15:15:12 | C91: 超级马力欧奥德赛 | D91: 卡带 | E91: 1063334622322 | F91: 出全新未拆封！Nintendo Switch 超级马里奥奥德 赛 港版中文卡带带原包装盒，正版实体，插卡即玩支持中文界面，动作冒险经典，剧情丰富，画面高清，家庭聚会、休闲娱乐都很适合！非偏远包邮，17点前当天发货喜欢直接拍，细节私聊 | G91: 227 | H91: 广东百分百好评 | J91: https://www.goofish.com/item?id=1063334622322&categoryId=201538503
A92: 2026-07-06 | B92: 2026-07-06 15:15:12 | C92: 超级马力欧奥德赛 | D92: 卡带 | E92: 1063215410204 | F92: 全新未拆封超级马里奥奥德赛 港版中文实体卡带 带原装盒 支持中文动作冒险经典 帽子附身玩法 支持1-2人本地/在线联机卡带保存很好 插卡即玩 功能正常包邮 可自提喜欢直接拍 细节私聊 | G92: 230 | H92: 浙江百分百好评 | J92: https://www.goofish.com/item?id=1063215410204&categoryId=201538503
A93: 2026-07-06 | B93: 2026-07-06 15:15:12 | C93: 超级马力欧奥德赛 | D93: 卡带 | E93: 1064163925673 | F93: 二手 Switch 超级马里奥 奥德赛 有外包装盒没有封面 感兴趣的话点“我想要”和我私聊吧～ | G93: 204 | H93: 广东百分百好评 | J93: https://www.goofish.com/item?id=1064163925673&categoryId=201538503
A94: 2026-07-06 | B94: 2026-07-06 15:15:12 | C94: 超级马力欧奥德赛 | D94: 卡带 | E94: 1063010985916 | F94: 全新未拆包邮】日版任天堂Switch 超级马里奥 奥德赛，带 原装盒全新未拆封 八角尖尖完好 包邮全新 | G94: 228 | H94: 北京百分百好评 | J94: https://www.goofish.com/item?id=1063010985916&categoryId=201538503
A95: 2026-07-06 | B95: 2026-07-06 15:15:12 | C95: 超级马力欧奥德赛 | D95: 卡带 | E95: 1065013700827 | F95: Switch 超级马里奥奥德赛 港版卡带，通关出了，全新未拆 封，带原装盒，卡带保存很好，正版实体卡带，功能正常，支持所有Switch主机（不含国行），中文界面，动作冒险类，玩法丰富，支持amiibo联动，适合家庭聚会、朋友一起玩。非偏远包邮同城自提便宜5元不议价喜欢直接拍，细节私聊 | G95: 225 | H95: 浙江卖家信用极好 | J95: https://www.goofish.com/item?id=1065013700827&categoryId=201538503
A96: 2026-07-06 | B96: 2026-07-06 15:15:12 | C96: 超级马力欧奥德赛 | D96: 卡带 | E96: 1063282870045 | F96: 全新未拆 当日发货 Switch超级马里奥奥德赛港版中文卡带 任天堂Switch游戏《超级马里奥奥德赛》港版中文实体卡带，带原装包装盒，塑封完好，支持中文界面，插卡即玩，功能正常。 | G96: 225 | H96: 河南百分百好评 | J96: https://www.goofish.com/item?id=1063282870045&categoryId=201538503
A97: 2026-07-06 | B97: 2026-07-06 15:15:12 | C97: 超级马力欧奥德赛 | D97: 卡带 | E97: 1065461040303 | F97: 高价上门回收相机，镜头，摄影机，运动相机，大疆无人机，口袋相 机，运动相机，数码相机，单反相机，单反镜头等数码摄影器材，免费上门回收，外地谈好价格先打款再发货。上门直接拿！各类数码产品都可以回收！全国连锁实体店，诚信经营。高价上门回收佳能，尼康，索尼，富士，松下，奥林巴斯，徕卡，哈苏，相机数码，适马，腾龙，唯卓仕，相机镜头，摄像机，稳定器，运动相机 ，ccd卡片机，口袋相机，稳定器，大疆无人机，平 | H97: 浙江 | J97: https://www.goofish.com/item?id=1065461040303&categoryId=201455413
A98: 2026-07-06 | B98: 2026-07-06 15:15:12 | C98: 超级马力欧奥德赛 | D98: 卡带 | E98: 1065460816451 | F98: 高价上门回收相机，镜头，摄影机，运动相机，大疆无人机，口袋相 机，运动相机，数码相机，单反相机，单反镜头等数码摄影器材，免费上门回收，外地谈好价格先打款再发货。上门直接拿！各类数码产品都可以回收！全国连锁实体店，诚信经营。高价上门回收佳能，尼康，索尼，富士，松下，奥林巴斯，徕卡，哈苏，相机数码，适马，腾龙，唯卓仕，相机镜头，摄像机，稳定器，运动相机 ，ccd卡片机，口袋相机，稳定器，大疆无人机，平 | H98: 湖北 | J98: https://www.goofish.com/item?id=1065460816451&categoryId=201455413
A99: 2026-07-06 | B99: 2026-07-06 15:15:12 | C99: 超级马力欧奥德赛 | D99: 卡带 | E99: 1065460664795 | F99: 高价上门回收相机，镜头，摄影机，运动相机，大疆无人机，口袋相 机，运动相机，数码相机，单反相机，单反镜头等数码摄影器材，免费上门回收，外地谈好价格先打款再发货。上门直接拿！各类数码产品都可以回收！全国连锁实体店，诚信经营。高价上门回收佳能，尼康，索尼，富士，松下，奥林巴斯，徕卡，哈苏，相机数码，适马，腾龙，唯卓仕，相机镜头，摄像机，稳定器，运动相机 ，ccd卡片机，口袋相机，稳定器，大疆无人机，平 | H99: 宁夏 | J99: https://www.goofish.com/item?id=1065460664795&categoryId=201455413
A100: 2026-07-06 | B100: 2026-07-06 15:15:12 | C100: 超级马力欧奥德赛 | D100: 卡带 | E100: 1064509289583 | F100: 高价上门回收相机，镜头，摄影机，运动相机，大疆无人机，口袋相 机，运动相机，数码相机，单反相机，单反镜头等数码摄影器材，免费上门回收，外地谈好价格先打款再发货。上门直接拿！各类数码产品都可以回收！全国连锁实体店，诚信经营。高价上门回收佳能，尼康，索尼，富士，松下，奥林巴斯，徕卡，哈苏，相机数码，适马，腾龙，唯卓仕，相机镜头，摄像机，稳定器，运动相机 ，ccd卡片机，口袋相机，稳定器，大疆无人机，平 | H100: 青海 | J100: https://www.goofish.com/item?id=1064509289583&categoryId=201455413
A101: 2026-07-06 | B101: 2026-07-06 15:15:12 | C101: 超级马力欧奥德赛 | D101: 卡带 | E101: 1063503062192 | F101: 高价上门回收相机，镜头，摄影机，运动相机，大疆无人机，口袋相 机，运动相机，数码相机，单反相机，单反镜头等数码摄影器材，免费上门回收，外地谈好价格先打款再发货。上门直接拿！各类数码产品都可以回收！全国连锁实体店，诚信经营。高价上门回收佳能，尼康，索尼，富士，松下，奥林巴斯，徕卡，哈苏，相机数码，适马，腾龙，唯卓仕，相机镜头，摄像机，稳定器，运动相机 ，ccd卡片机，口袋相机，稳定器，大疆无人机，平 | H101: 辽宁 | J101: https://www.goofish.com/item?id=1063503062192&categoryId=201455413
A102: 2026-07-06 | B102: 2026-07-06 15:15:12 | C102: 超级马力欧奥德赛 | D102: 卡带 | E102: 1064809976968 | F102: Switch 超级马里奥奥德赛 港版中文卡带 全新未拆封，带原装盒支持Switch主机，插卡即玩，动作冒险类正版实体卡带，包装完整包邮，可自提售出不退 | G102: 225 | H102: 湖北百分百好评 | J102: https://www.goofish.com/item?id=1064809976968&categoryId=201538503
A103: 2026-07-06 | B103: 2026-07-06 15:15:12 | C103: 超级马力欧奥德赛 | D103: 卡带 | E103: 1063330906547 | F103: Switch游戏卡带合集，喵喵大作战和马里奥+疯狂兔子 希望 之星 宇宙版，两个都是正版实体卡带，带原装盒，成色几乎全新，外观很新，保存很好，插上即玩，支持所有Switch主机，中文界面，内容丰富，适合喜欢猫咪和马里奥系列的朋友。猫咪大作战拆封未上机，马里奥未拆封马里奥80包邮，猫咪60包邮，两盘一起拿的话130包邮。价格不刀！非偏远包邮，售出不退。需要细节图私聊。 | G103: 80 | H103: 陕西回复超快 | J103: https://www.goofish.com/item?id=1063330906547&categoryId=201538503
A104: 2026-07-06 | B104: 2026-07-06 15:15:41 | C104: 集合啦！动物森友会 | D104: 卡带 | E104: 1065420036375 | F104: switch原装手柄一对，joycon，正版，正版，正版，机 子卖掉了找出来的，手柄是备用的，基本没怎么用，功能都正常，别拿国产比价格，不在一个档次，看上的请联系，标价是一对的价格，嫌贵的别联系。 | G104: 188 | H104: 广东百分百好评 | J104: https://www.goofish.com/item?id=1065420036375&categoryId=126920145
A105: 2026-07-06 | B105: 2026-07-06 15:15:41 | C105: 集合啦！动物森友会 | D105: 卡带 | E105: 1064507365132 | F105: 拳霸Q4大师赛纪念版街机摇杆，红黑蝙蝠面板，三和全配，原装球 头，按键灵敏摇杆顺滑，支持PC/PS3/Switch/手机，打格斗游戏用，成色还可以，需要来拍 | G105: 260 | H105: 云南 | J105: https://www.goofish.com/item?id=1064507365132&categoryId=126856341
A106: 2026-07-06 | B106: 2026-07-06 15:15:41 | C106: 集合啦！动物森友会 | D106: 卡带 | E106: 1063489942707 | F106: 几乎全新，仅使用过一次 感兴趣的话点“我想要”和我私聊吧～ | G106: 370 | H106: 江苏百分百好评 | J106: https://www.goofish.com/item?id=1063489942707&categoryId=126920145
A107: 2026-07-06 | B107: 2026-07-06 15:15:41 | C107: 集合啦！动物森友会 | D107: 卡带 | E107: 1064272449559 | F107: 极想switch1代只只猪鸡摇杆帽 未使用过 默认有官瑕标价包邮非偏远 可直拍 | G107: 88 | H107: 浙江百分百好评 | J107: https://www.goofish.com/item?id=1064272449559&categoryId=126856341
A108: 2026-07-06 | B108: 2026-07-06 15:15:41 | C108: 集合啦！动物森友会 | D108: 卡带 | E108: 1063339926109 | F108: 99新 NS Joy-Con手柄 粉色一对，带猫爪摇杆帽和手 绳使用次数估计就个位数。原来的盒装丢了，之前没打算出百亿补贴渠道购入，原装正品，福州发货，普快包邮售出不退不换，有问题请提供完整开箱视频 | G108: 238 | H108: 福建百分百好评 | J108: https://www.goofish.com/item?id=1063339926109&categoryId=126920145
A109: 2026-07-06 | B109: 2026-07-06 15:15:41 | C109: 集合啦！动物森友会 | D109: 卡带 | E109: 1065421152662 | F109: Nintendo Switch任天堂Joy-Con游戏手柄体 感震动无线蓝牙即插即用颜色：电光紫+电光橙全套 仅拆封 未使用 图片实物实拍 所见即所得 正品保真 假一赔十 支持各种鉴定 便宜出 捡漏的来 包邮 注意事项： 贵重物品 发出不退不换 不支持7天无理由 下单请考虑清楚一般默认发中通，偏远地区和需要顺丰，京东可以联系方式补差价发货。偏远地区：西藏；内蒙古；宁夏；海南；甘肃；新疆 | G109: 369 | H109: 湖北 | J109: https://www.goofish.com/item?id=1065421152662&categoryId=126920145
A110: 2026-07-06 | B110: 2026-07-06 15:15:41 | C110: 集合啦！动物森友会 | D110: 卡带 | E110: 1064504253799 | F110: 北通鲲鹏20无线手柄，绝尘白，几乎全新，无线蓝牙连接，支持P C、Switch、手机、电视，TMR摇杆，机械按键2.0，全向十字键，扳机震动，打游戏手感好，按键灵敏，外观没磕碰暗伤，功能正常配件齐全，有需要的来聊，价格可谈～ | G110: 120 | H110: 辽宁发货极快 | J110: https://www.goofish.com/item?id=1064504253799&categoryId=126920145
A111: 2026-07-06 | B111: 2026-07-06 15:15:41 | C111: 集合啦！动物森友会 | D111: 卡带 | E111: 1065437996101 | F111: switch原装正品手柄一对 功能正常，摇杆不漂移包邮不刀 | G111: 166 | H111: 江苏 | J111: https://www.goofish.com/item?id=1065437996101&categoryId=126920145
A112: 2026-07-06 | B112: 2026-07-06 15:15:41 | C112: 集合啦！动物森友会 | D112: 卡带 | E112: 1065429828869 | F112: Switch Joy-Con 荧光蓝色/荧光黄 成色很好，没使用，看好再拍，售出不退换 | G112: 236 | H112: 天津百分百好评 | J112: https://www.goofish.com/item?id=1065429828869&categoryId=126920145
A113: 2026-07-06 | B113: 2026-07-06 15:15:41 | C113: 集合啦！动物森友会 | D113: 卡带 | E113: 1064033889835 | F113: 任天堂switch原装joycon手柄 动森限定蓝绿手柄jo y，原装正品，支持验货，功能正常，默认橙色一般，可以测试在发货，包邮不议价。 | G113: 180 | H113: 广东卖家信用极好 | J113: https://www.goofish.com/item?id=1064033889835&categoryId=126920145
... A153: 2026-07-06 | B153: 2026-07-06 15:16:51 | C153: 宝可梦 朱 | D153: 卡带 | E153: 1063851812358 | F153: 个人闲置 Switch 港版宝可梦朱+盾，带原装盒，卡带成色 还可以，功能正常，插卡即玩，支持所有Switch主机，中文界面，剧情丰富，宝可梦超多，支持联机，适合喜欢宝可梦和聚会的朋友同城可自提 喜欢直接拍，细节私聊～ | G153: 320 | H153: 新疆百分百好评 | J153: https://www.goofish.com/item?id=1063851812358&categoryId=201538503
A154: 2026-07-06 | B154: 2026-07-06 15:16:51 | C154: 宝可梦 朱 | D154: 卡带 | E154: 1061828810684 | F154: 【包邮】Switch 宝可梦朱 中文 封面有瑕疵 实物图拍摄喜欢直接拍，有问题私聊 | H154: 北京卖家信用极好 | J154: https://www.goofish.com/item?id=1061828810684&categoryId=201538503
A155: 2026-07-06 | B155: 2026-07-06 15:16:51 | C155: 宝可梦 朱 | D155: 卡带 | E155: 1062310223048 | F155: 宝可梦紫 Switch 港版中文卡带，带原装盒，卡带插拔次数 少，功能正常。支持所有Switch主机，插卡即玩，适合宝可梦粉补坑或收藏。包邮，可自提。喜欢直接拍，细节私聊。不接受到手刀 | G155: 181 | H155: 天津 | J155: https://www.goofish.com/item?id=1062310223048&categoryId=201538503
A156: 2026-07-06 | B156: 2026-07-06 15:16:51 | C156: 宝可梦 朱 | D156: 卡带 | E156: 1063873544976 | F156: Switch 宝可梦朱 港版中文卡带 带原装盒 支持所有Switch主机 插卡即玩 联机正常成色还可以 卡带盘面干净 功能正常 没怎么用包邮 同城可自提 价格可聊喜欢直接拍 细节私聊 | G156: 170 | H156: 河南 | J156: https://www.goofish.com/item?id=1063873544976&categoryId=201538503
A157: 2026-07-06 | B157: 2026-07-06 15:16:51 | C157: 宝可梦 朱 | D157: 卡带 | E157: 1064145713738 | F157: 宝可梦紫Switch卡带，港版中文，带原装盒，插卡即玩，支持 所有Switch主机，国行/港版/日版都能用。正版实体卡带，单张，未通关，联机没问题，盒子有轻微破损。包邮，支持自提。价格可聊，喜欢直接拍，细节私聊。 | G157: 195 | H157: 四川百分百好评 | J157: https://www.goofish.com/item?id=1064145713738&categoryId=201538503
A158: 2026-07-06 | B158: 2026-07-06 15:16:51 | C158: 宝可梦 朱 | D158: 卡带 | E158: 1064343153970 | F158: Switch 宝可梦紫 中文卡带，插卡即玩，正版实体，卡带保 存很好，功能正常，成色实图所拍，适合宝可梦粉丝补坑或收藏。RPG经典玩法，画面精美，支持本地无线联机，最多4人一起玩，喜欢的朋友欢迎私聊，细节图可发～二手卡带，功能正常，成色实图所拍，看准再下单，售出不退不换。非偏远地区包邮，偏远地区补差5元，售后需要提供完整开箱视频 | G158: 180 | H158: 广东卖家信用极好 | J158: https://www.goofish.com/item?id=1064343153970&categoryId=201538503
A159: 2026-07-06 | B159: 2026-07-06 15:16:51 | C159: 宝可梦 朱 | D159: 卡带 | E159: 1064263660208 | F159: 几乎全新 Switch《宝可梦 朱》实体卡带，带原装盒，插卡 即玩，支持所有Switch主机（国行/港版/日版/欧版通用），中文界面，内容全，精灵收集养成，剧情丰富，宝可梦系列必收！正版保证，收藏自用都合适，盒子保存很好，没啥痕迹，卡带正常读取，放心入手～包邮，同城可自提喜欢直接拍，细节图私聊发～售出不退不换还卖其他游戏，支持回收，需要可以私聊～ | G159: 175 | H159: 河南百分百好评 | J159: https://www.goofish.com/item?id=1064263660208&categoryId=201538503
A160: 2026-07-06 | B160: 2026-07-06 15:16:51 | C160: 宝可梦 朱 | D160: 卡带 | E160: 1064969132866 | F160: 几乎全新Switch《宝可梦 朱》港版实体卡带，带原装盒，盘 面很新，保存很好，正版保证。支持所有Switch主机，插卡即玩，中文界面，RPG经典，玩法丰富，适合宝可梦系列粉丝收藏或自用。支持自提，外地可邮寄二手商品售出不退不换需要细节图可私聊，喜欢直接拍 | G160: 175 | H160: 江苏百分百好评 | J160: https://www.goofish.com/item?id=1064969132866&categoryId=201538503
A161: 2026-07-06 | B161: 2026-07-06 15:16:51 | C161: 宝可梦 朱 | D161: 卡带 | E161: 1064216153027 | F161: （面交自提）宝可梦朱Switch港版中文卡带任天堂Switc h游戏《宝可梦朱》港版中文实体卡带，带原装盒，卡带外观完好，插拔功能正常，支持联机，适合收藏或日常游玩。 | G161: 140 | H161: 福建 | J161: https://www.goofish.com/item?id=1064216153027&categoryId=201538503
A162: 2026-07-06 | B162: 2026-07-06 15:16:51 | C162: 宝可梦 朱 | D162: 卡带 | E162: 1062025103049 | F162: 宝可梦紫同捆Dlc，Switch实体卡带，带原包装盒，保存很 新，插拔次数少，功能正常，适合宝可梦系列粉丝。包邮，也可以自提，二手物品售出不退换 | G162: 390 | H162: 山东 | J162: https://www.goofish.com/item?id=1062025103049&categoryId=201538503
A163: 2026-07-06 | B163: 2026-07-06 15:16:51 | C163: 宝可梦 朱 | D163: 卡带 | E163: 1062550023876 | F163: 出Switch宝可梦朱卡带，港版中文，带原装盒，成色几乎全新 ，保存很好，插卡即玩，支持中文和联机，国行Switch也能用，功能正常，喜欢宝可梦的可以看看～包邮！支持自提细节图可以私聊发，喜欢直接拍，随时问我～ | G163: 200 | H163: 上海百分百好评 | J163: https://www.goofish.com/item?id=1062550023876&categoryId=201538503
A164: 2026-07-06 | B164: 2026-07-06 15:16:51 | C164: 宝可梦 朱 | D164: 卡带 | E164: 1062530619188 | F164: 宝可梦朱Switch卡带任天堂Switch游戏《宝可梦朱》港 版实体卡带，带原装盒，封面图案清晰，边角无明显磨损，支持中文，兼容所有Switch主机。二手自用，非商家，买出不退不换。 | G164: 180 | H164: 浙江卖家信用极好 | J164: https://www.goofish.com/item?id=1062530619188&categoryId=201538503
A165: 2026-07-06 | B165: 2026-07-06 15:16:51 | C165: 宝可梦 朱 | D165: 卡带 | E165: 1063415817486 | F165: 宝可梦朱Switch卡带 任天堂Switch游戏《宝可梦朱》实体卡带，带原装盒，卡带金手指无氧化，盘面干净，功能正常，支持中文，可兼容所有Switch主机。 | G165: 180 | H165: 吉林百分百好评 | J165: https://www.goofish.com/item?id=1063415817486&categoryId=201538503
A166: 2026-07-06 | B166: 2026-07-06 15:16:51 | C166: 宝可梦 朱 | D166: 卡带 | E166: 1065185256842 | F166: 全新未拆封switch 宝可梦朱， 日版中文，原装盒子都在， 正版实体卡带，插卡即玩～日版中文，支持所有Switch主机，经典RPG玩法，开放世界探索，多人联机乐趣多多，适合宝可梦系列粉丝收藏自用！包邮发货，喜欢直接拍，细节图私聊发～ | G166: 195 | H166: 广西百分百好评 | J166: https://www.goofish.com/item?id=1065185256842&categoryId=201538503
A167: 2026-07-06 | B167: 2026-07-06 15:16:51 | C167: 宝可梦 朱 | D167: 卡带 | E167: 1062287915088 | F167: 绚烂传说 繁中卡带 拔插一次，带盒，保存很好非偏远包邮，长沙可自提 | G167: 295 | H167: 湖南百分百好评 | J167: https://www.goofish.com/item?id=1062287915088&categoryId=201538503
A168: 2026-07-06 | B168: 2026-07-06 15:16:51 | C168: 宝可梦 朱 | D168: 卡带 | E168: 1061722438607 | F168: Switch宝可梦朱日版和宝可梦盾港版盒子。无卡带，单买10 块不包邮包邮，同城可自提，喜欢直接拍，细节私聊发图～ | H168: 北京 | J168: https://www.goofish.com/item?id=1061722438607&categoryId=201538503
A169: 2026-07-06 | B169: 2026-07-06 15:16:51 | C169: 宝可梦 朱 | D169: 卡带 | E169: 1064487384961 | F169: 几乎全新宝可梦斯卡雷特Switch卡带，日版，带原装盒，支持 中文，插卡即玩，保存很好，盒子很新，适配所有Switch主机，经典RPG冒险，剧情丰富，联机没问题。包邮，也可以自提。价格可聊，喜欢私聊～ | G169: 163 | H169: 江苏 | J169: https://www.goofish.com/item?id=1064487384961&categoryId=201538503
A170: 2026-07-06 | B170: 2026-07-06 15:16:51 | C170: 宝可梦 朱 | D170: 卡带 | E170: 1062746901012 | F170: 宝可梦紫 Switch卡带 ns 购于澳大利亚实体店 支持中文 所见即所得卡带看着很新的 盒子对光看有些划痕（如最后两张图）没有破损 算正常痕迹吧 介意这个的请勿拍 包邮 深圳也可面交 欢迎直拍 有问题欢迎私聊 二手不退换 | G170: 179 | H170: 广东百分百好评 | J170: https://www.goofish.com/item?id=1062746901012&categoryId=201538503
A171: 2026-07-06 | B171: 2026-07-06 15:16:51 | C171: 宝可梦 朱 | D171: 卡带 | E171: 1062833413113 | F171: 【包邮】宝可梦紫+零之秘宝DLC同捆 港版印刷封面 实物图拍摄喜欢直接拍，售出不退不换 | H171: 北京卖家信用极好 | J171: https://www.goofish.com/item?id=1062833413113&categoryId=201538503
A172: 2026-07-06 | B172: 2026-07-06 15:16:51 | C172: 宝可梦 朱 | D172: 卡带 | E172: 1062524959238 | F172: 出宝可梦紫卡带 日版Switch卡带 带盒 仅拆保存好 功能正常 支持中文 国行可用拍下后发送金手指状态标价已包手续费邮费 主页满百包邮喜欢可直拍 | G172: 181.09 | H172: 浙江百分百好评 | J172: https://www.goofish.com/item?id=1062524959238&categoryId=201538503
A173: 2026-07-06 | B173: 2026-07-06 15:16:51 | C173: 宝可梦 朱 | D173: 卡带 | E173: 1065324092114 | F173: 宝可梦紫Switch卡带，带原装盒，插卡即玩，支持中文，内容 齐全，功能正常。盒子和卡带都很新，没怎么用过，成色挺好。包邮，可自提，喜欢直接拍，细节私聊。 | G173: 222 | H173: 新疆 | J173: https://www.goofish.com/item?id=1065324092114&categoryId=201538503
A174: 2026-07-06 | B174: 2026-07-06 15:16:51 | C174: 宝可梦 朱 | D174: 卡带 | E174: 1062544102589 | F174: Switch游戏卡带一批 空洞骑士 宝可梦朱 宝可梦朱+dlc 超级马里奥3D世界 星之卡比探索发现 马里奥party 空洞骑士150 带地图宝可梦朱+dlc 375 盒子被小猫咬坏了一些，如图。卡带只插过一次，不爱玩，直接出了。超级马里奥3D世界180星之卡比探索发现 200马里奥party 盒子右下角有个裂卡带无任何问题 200都有中文，带原包装盒，成色很新，外观很新，保存很好正版卡带，插卡即 | G174: 150 | H174: 北京百分百好评 | J174: https://www.goofish.com/item?id=1062544102589&categoryId=201538503
A175: 2026-07-06 | B175: 2026-07-06 15:16:51 | C175: 宝可梦 朱 | D175: 卡带 | E175: 1065422204334 | F175: 【出】任天堂switch1&2实体游戏卡带（塞尔达传说：旷野 之息、塞尔达传说：王国之泪、空洞骑士、宝可梦朱紫、宝可梦传说：阿尔宙斯、宝可梦传说：ZA）日版港版卡带，带原装盒（部分包含宣传卡），保存很好，插上就能玩，支持中文，动作冒险经典，收藏自用都合适。*包邮出，全程录像打包发货（收货售出后不退不换）需要可以联系私聊～一次多买打包更优惠 | G175: 240 | H175: 河南百分百好评 | J175: https://www.goofish.com/item?id=1065422204334&categoryId=201538503
A176: 2026-07-06 | B176: 2026-07-06 15:17:19 | C176: 宝可梦 紫 | D176: 卡带 | E176: 1065306684367 | F176: Switch 宝可梦紫 港版中文卡带，插卡即玩，支持中文，联 机没问题，功能正常，成色实图所拍，保存很好，适合宝可梦粉和RPG玩家收藏或自用。二手卡带，功能正常，成色实图所拍，看准再下单，售出不退不换。非偏远地区包邮，偏远地区补差5元，售后需要提供完整开箱视频 | G176: 180 | H176: 广东卖家信用极好 | J176: https://www.goofish.com/item?id=1065306684367&categoryId=201538503
A177: 2026-07-06 | B177: 2026-07-06 15:17:19 | C177: 宝可梦 紫 | D177: 卡带 | E177: 1062310223048 | F177: 宝可梦紫 Switch 港版中文卡带，带原装盒，卡带插拔次数 少，功能正常。支持所有Switch主机，插卡即玩，适合宝可梦粉补坑或收藏。包邮，可自提。喜欢直接拍，细节私聊。不接受到手刀 | G177: 181 | H177: 天津 | J177: https://www.goofish.com/item?id=1062310223048&categoryId=201538503
A178: 2026-07-06 | B178: 2026-07-06 15:17:19 | C178: 宝可梦 紫 | D178: 卡带 | E178: 1063402073507 | F178: Switch 日版《宝可梦 紫》卡带，带原包装盒，正版实体， 支持中文，插卡即玩，联机没问题。卡带外观干净，插拔正常，功能正常，保存很好。适合Switch主机，宝可梦粉推荐。 | G178: 179 | H178: 江苏百分百好评 | J178: https://www.goofish.com/item?id=1063402073507&categoryId=201538503
...

Sheet 价格统计
A1: 游戏名 | B1: 版本 | C1: 最低价 | D1: 最高价 | E1: 平均价 | F1: 记录数 | G1: 最近抓取日期
A2: 塞尔达传说：王国之泪 | B2: 卡带 | C2: =MINIFS(价格历史!G:G,价格历史!C:C,A2) | D2: =MAXIFS(价格历史!G:G,价格历史!C:C,A2) | E2: =AVERAGEIF(价格历史!C:C,A2,价格历史!G:G) | F2: =COUNTIF(价格历史!C:C,A2) | G2: =MAXIFS(价格历史!A:A,价格历史!C:C,A2)
A3: 塞尔达传说：旷野之息 | B3: 卡带 | C3: =MINIFS(价格历史!G:G,价格历史!C:C,A3) | D3: =MAXIFS(价格历史!G:G,价格历史!C:C,A3) | E3: =AVERAGEIF(价格历史!C:C,A3,价格历史!G:G) | F3: =COUNTIF(价格历史!C:C,A3) | G3: =MAXIFS(价格历史!A:A,价格历史!C:C,A3)
A4: 马力欧卡丁车8豪华版 | B4: 卡带 | C4: =MINIFS(价格历史!G:G,价格历史!C:C,A4) | D4: =MAXIFS(价格历史!G:G,价格历史!C:C,A4) | E4: =AVERAGEIF(价格历史!C:C,A4,价格历史!G:G) | F4: =COUNTIF(价格历史!C:C,A4) | G4: =MAXIFS(价格历史!A:A,价格历史!C:C,A4)
A5: 超级马力欧奥德赛 | B5: 卡带 | C5: =MINIFS(价格历史!G:G,价格历史!C:C,A5) | D5: =MAXIFS(价格历史!G:G,价格历史!C:C,A5) | E5: =AVERAGEIF(价格历史!C:C,A5,价格历史!G:G) | F5: =COUNTIF(价格历史!C:C,A5) | G5: =MAXIFS(价格历史!A:A,价格历史!C:C,A5)
A6: 集合啦！动物森友会 | B6: 卡带 | C6: =MINIFS(价格历史!G:G,价格历史!C:C,A6) | D6: =MAXIFS(价格历史!G:G,价格历史!C:C,A6) | E6: =AVERAGEIF(价格历史!C:C,A6,价格历史!G:G) | F6: =COUNTIF(价格历史!C:C,A6) | G6: =MAXIFS(价格历史!A:A,价格历史!C:C,A6)
A7: 任天堂明星大乱斗 特别版 | B7: 卡带 | C7: =MINIFS(价格历史!G:G,价格历史!C:C,A7) | D7: =MAXIFS(价格历史!G:G,价格历史!C:C,A7) | E7: =AVERAGEIF(价格历史!C:C,A7,价格历史!G:G) | F7: =COUNTIF(价格历史!C:C,A7) | G7: =MAXIFS(价格历史!A:A,价格历史!C:C,A7)
A8: 宝可梦 朱 | B8: 卡带 | C8: =MINIFS(价格历史!G:G,价格历史!C:C,A8) | D8: =MAXIFS(价格历史!G:G,价格历史!C:C,A8) | E8: =AVERAGEIF(价格历史!C:C,A8,价格历史!G:G) | F8: =COUNTIF(价格历史!C:C,A8) | G8: =MAXIFS(价格历史!A:A,价格历史!C:C,A8)
A9: 宝可梦 紫 | B9: 卡带 | C9: =MINIFS(价格历史!G:G,价格历史!C:C,A9) | D9: =MAXIFS(价格历史!G:G,价格历史!C:C,A9) | E9: =AVERAGEIF(价格历史!C:C,A9,价格历史!G:G) | F9: =COUNTIF(价格历史!C:C,A9) | G9: =MAXIFS(价格历史!A:A,价格历史!C:C,A9)
A10: 宝可梦 剑 | B10: 卡带 | C10: =MINIFS(价格历史!G:G,价格历史!C:C,A10) | D10: =MAXIFS(价格历史!G:G,价格历史!C:C,A10) | E10: =AVERAGEIF(价格历史!C:C,A10,价格历史!G:G) | F10: =COUNTIF(价格历史!C:C,A10) | G10: =MAXIFS(价格历史!A:A,价格历史!C:C,A10)
A11: 宝可梦 盾 | B11: 卡带 | C11: =MINIFS(价格历史!G:G,价格历史!C:C,A11) | D11: =MAXIFS(价格历史!G:G,价格历史!C:C,A11) | E11: =AVERAGEIF(价格历史!C:C,A11,价格历史!G:G) | F11: =COUNTIF(价格历史!C:C,A11) | G11: =MAXIFS(价格历史!A:A,价格历史!C:C,A11)
A12: 异度神剑3 | B12: 卡带 | C12: =MINIFS(价格历史!G:G,价格历史!C:C,A12) | D12: =MAXIFS(价格历史!G:G,价格历史!C:C,A12) | E12: =AVERAGEIF(价格历史!C:C,A12,价格历史!G:G) | F12: =COUNTIF(价格历史!C:C,A12) | G12: =MAXIFS(价格历史!A:A,价格历史!C:C,A12)
A13: 异度神剑2 | B13: 卡带 | C13: =MINIFS(价格历史!G:G,价格历史!C:C,A13) | D13: =MAXIFS(价格历史!G:G,价格历史!C:C,A13) | E13: =AVERAGEIF(价格历史!C:C,A13,价格历史!G:G) | F13: =COUNTIF(价格历史!C:C,A13) | G13: =MAXIFS(价格历史!A:A,价格历史!C:C,A13)
... A35: 口袋妖怪 宝可梦传说Z-A | B35: 卡带 | C35: =MINIFS(价格历史!G:G,价格历史!C:C,A35) | D35: =MAXIFS(价格历史!G:G,价格历史!C:C,A35) | E35: =AVERAGEIF(价格历史!C:C,A35,价格历史!G:G) | F35: =COUNTIF(价格历史!C:C,A35) | G35: =MAXIFS(价格历史!A:A,价格历史!C:C,A35)

Sheet 游戏价格汇总
A1: 游戏名 | B1: 版本 | C1: 样本数 | D1: 参考价 | E1: 最低价 | F1: 最高价 | G1: 平均价 | H1: 抓取日期
A2: 任天堂明星大乱斗 特别版 | B2: 卡带 | C2: 185 | D2: 220 | E2: 64 | F2: 950 | G2: 226.79 | H2: 2026-07-06 21:05:26
A3: 塞尔达传说：旷野之息 | B3: 卡带 | C3: 149 | D3: 224 | E3: 50 | F3: 495 | G3: 213.33 | H3: 2026-07-06 21:05:26
A4: 塞尔达传说：王国之泪 | B4: 卡带 | C4: 142 | D4: 238 | E4: 55 | F4: 520 | G4: 247.44 | H4: 2026-07-06 21:05:26
A5: 宝可梦 剑 | B5: 卡带 | C5: 170 | D5: 197 | E5: 84 | F5: 800 | G5: 207.95 | H5: 2026-07-06 21:05:26
A6: 宝可梦 朱 | B6: 卡带 | C6: 170 | D6: 183 | E6: 60 | F6: 700 | G6: 208.76 | H6: 2026-07-06 21:05:26
A7: 宝可梦 盾 | B7: 卡带 | C7: 172 | D7: 179 | E7: 60 | F7: 999 | G7: 241.44 | H7: 2026-07-06 21:05:26
A8: 宝可梦 紫 | B8: 卡带 | C8: 162 | D8: 183 | E8: 60 | F8: 1010 | G8: 226.62 | H8: 2026-07-06 21:05:26
A9: 超级马力欧奥德赛 | B9: 卡带 | C9: 178 | D9: 235 | E9: 65 | F9: 833 | G9: 213.15 | H9: 2026-07-06 21:05:26
A10: 集合啦！动物森友会 | B10: 卡带 | C10: 165 | D10: 183 | E10: 50 | F10: 799 | G10: 207.86 | H10: 2026-07-06 21:05:26
A11: 马力欧卡丁车8豪华版 | B11: 卡带 | C11: 186 | D11: 206 | E11: 60 | F11: 550 | G11: 208.89 | H11: 2026-07-06 21:05:26
